{
	"profiles": [
		{
			"firstname": "Veli",
			"lastname": "Lehtisalo",
			"email": "eveliina02@luukku.com",
			"phone": "+4070510715668",
			"birthday": "1942-03-21",
			"sexualPreference":"Hetero",
			"gender": "male",
			"biography": "Take your choice!' The Duchess took no notice of her hedgehog. The hedgehog was engaged in a hurry that she was peering about anxiously among the bright flower-beds and the bright flower-beds and.",
			"address": {
				"street": "Seijakierros 66 928",
				"streetName": "Uosukainenkaarto",
				"buildingNumber": "5",
				"city": "Juhopudas",
				"zipcode": "61833",
				"country": "Gambia",
				"county_code": "PT",
				"latitude": 60.27199,
				"longitude": 24.613166
			},
			"website": "http:\/\/tapio.fi",
			"pictures": ["http:\/\/placeimg.com\/640\/480\/people", "http:\/\/placeimg.com\/640\/480\/people", "http:\/\/placeimg.com\/640\/480\/people"]

		},
		{
			"firstname": "Onni",
			"lastname": "Aaltonen",
			"email": "leskinen.julius@koskela.info",
			"phone": "+5272752206941",
			"birthday": "1936-02-23",
			"sexualPreference":"Hetero",
			"gender": "male",
			"biography": "That WILL be a queer thing, to be afraid of it. Presently the Rabbit asked. 'No, I didn't,' said Alice: 'three inches is such a simple question,' added the Dormouse. 'Fourteenth of March, I think I.",
			"address": {
				"street": "Jimisilta 1 329",
				"streetName": "Ellapolku",
				"buildingNumber": "3449",
				"city": "Etel\u00e4-Danielpudas",
				"zipcode": "41311",
				"country": "Pohjois-Korea",
				"county_code": "VU",
				"latitude": -17.672706,
				"longitude": 50.898716
			},
			"website": "http:\/\/attila.org",
			"pictures": ["http:\/\/placeimg.com\/640\/480\/people", "http:\/\/placeimg.com\/640\/480\/people", "http:\/\/placeimg.com\/640\/480\/people"]

		},
		{
			"firstname": "Aake",
			"lastname": "Kujanp\u00e4\u00e4",
			"email": "pirttijarvi.hampus@armio.com",
			"phone": "+1294459344912",
			"birthday": "1942-03-16",
			"sexualPreference":"Bi",
			"gender": "male",
			"biography": "I used--and I don't keep the same thing a bit!' said the Caterpillar. 'Well, I've tried banks, and I've tried banks, and I've tried banks, and I've tried hedges,' the Pigeon in a hurried nervous.",
			"address": {
				"street": "Aarosilta 45 349",
				"streetName": "Malmivaarakaarto",
				"buildingNumber": "9695",
				"city": "Etel\u00e4-Roosaj\u00e4rvi",
				"zipcode": "83163",
				"country": "Italia",
				"county_code": "TC",
				"latitude": 35.967796,
				"longitude": 9.900668
			},
			"website": "http:\/\/tenkanen.com",
			"pictures": ["http:\/\/placeimg.com\/640\/480\/people", "http:\/\/placeimg.com\/640\/480\/people", "http:\/\/placeimg.com\/640\/480\/people"]

		},
		{
			"firstname": "Hilppa",
			"lastname": "Asikainen",
			"email": "heikki93@jippii.fi",
			"phone": "+1328585212660",
			"birthday": "1939-03-15",
			"gender": "female",
			"biography": "Normans--\" How are you thinking of?' 'I beg pardon, your Majesty,' said the Dormouse; '--well in.' This answer so confused poor Alice, that she tipped over the wig, (look at the end of trials.",
			"address": {
				"street": "Juliat\u00f6yry 3",
				"streetName": "Bellakuja",
				"buildingNumber": "0466",
				"city": "Vilmakyl\u00e4",
				"zipcode": "17047",
				"country": "Mauritius",
				"county_code": "BH",
				"latitude": 68.40702,
				"longitude": -19.130535
			},
			"website": "http:\/\/raisanen.com",
			"pictures": ["http:\/\/placeimg.com\/640\/480\/people", "http:\/\/placeimg.com\/640\/480\/people", "http:\/\/placeimg.com\/640\/480\/people"]

		},
		{
			"firstname": "Anni",
			"lastname": "Pirttikangas",
			"email": "santeri.attila@yahoo.com",
			"phone": "+8117279882658",
			"birthday": "1956-03-17",
			"sexualPreference":"Asexual",
			"gender": "female",
			"biography": "Then it got down off the fire, licking her paws and washing her face--and she is such a pleasant temper, and thought it must be a grin, and she jumped up in great disgust, and walked two and two, as.",
			"address": {
				"street": "Kautohaka 5923",
				"streetName": "Jannekuja",
				"buildingNumber": "31",
				"city": "Krapuharju",
				"zipcode": "99888",
				"country": "Mauritius",
				"county_code": "AI",
				"latitude": 4.82692,
				"longitude": 137.778379
			},
			"website": "http:\/\/lind.net",
			"pictures": ["http:\/\/placeimg.com\/640\/480\/people", "http:\/\/placeimg.com\/640\/480\/people", "http:\/\/placeimg.com\/640\/480\/people"]

		},
		{
			"firstname": "Sisu",
			"lastname": "Alahuhta",
			"email": "matias.pakkala@harju.net",
			"phone": "+7743381886041",
			"birthday": "1972-05-02",
			"sexualPreference":"Hetero",
			"gender": "male",
			"biography": "When the sands are all dry, he is gay as a boon, Was kindly permitted to pocket the spoon: While the Duchess sneezed occasionally; and as it spoke (it was exactly one a-piece all round. (It was this.",
			"address": {
				"street": "Ankkurikierros 3",
				"streetName": "Fannikatu",
				"buildingNumber": "6",
				"city": "M\u00e4ntyl\u00e4joki",
				"zipcode": "68230",
				"country": "Afganistan",
				"county_code": "LS",
				"latitude": 50.796106,
				"longitude": 79.270121
			},
			"website": "http:\/\/liukkonen.fi",
			"pictures": ["http:\/\/placeimg.com\/640\/480\/people", "http:\/\/placeimg.com\/640\/480\/people", "http:\/\/placeimg.com\/640\/480\/people"]

		},
		{
			"firstname": "Aappo",
			"lastname": "Nurmela",
			"email": "annu74@tuppurainen.fi",
			"phone": "+1309620232139",
			"birthday": "1967-07-11",
			"sexualPreference":"Hetero",
			"gender": "male",
			"biography": "The master was an immense length of neck, which seemed to be found: all she could even make out that it was over at last, with a sigh: 'he taught Laughing and Grief, they used to queer things.",
			"address": {
				"street": "Harjam\u00e4kikuja 3761",
				"streetName": "Ameliatie",
				"buildingNumber": "61",
				"city": "Anttisalmi",
				"zipcode": "57802",
				"country": "Makedonia",
				"county_code": "UG",
				"latitude": 42.87302,
				"longitude": 43.033312
			},
			"website": "http:\/\/einola.com",
			"pictures": ["http:\/\/placeimg.com\/640\/480\/people", "http:\/\/placeimg.com\/640\/480\/people", "http:\/\/placeimg.com\/640\/480\/people"]

		},
		{
			"firstname": "Teijo",
			"lastname": "Aittasalmi",
			"email": "ahtio.annu@hakala.com",
			"phone": "+5892444742458",
			"birthday": "1982-09-11",
			"sexualPreference":"Bi",
			"gender": "male",
			"biography": "FIT you,' said Alice, as she had made her draw back in a large one, but it makes me grow smaller, I can guess that,' she added in a bit.' 'Perhaps it doesn't matter which way it was too late to wish.",
			"address": {
				"street": "Hermannisilta 9",
				"streetName": "Levinhaka",
				"buildingNumber": "7",
				"city": "Tatulampi",
				"zipcode": "06815",
				"country": "Swazimaa",
				"county_code": "AL",
				"latitude": 78.254995,
				"longitude": 103.169708
			},
			"website": "http:\/\/kakkonen.com",
			"pictures": ["http:\/\/placeimg.com\/640\/480\/people", "http:\/\/placeimg.com\/640\/480\/people", "http:\/\/placeimg.com\/640\/480\/people"]

		},
		{
			"firstname": "Isto",
			"lastname": "It\u00e4vuori",
			"email": "savioja.ellen@puhakka.com",
			"phone": "+4822844131871",
			"birthday": "2012-09-05",
			"sexualPreference":"Gay",
			"gender": "male",
			"biography": "Queen. 'You make me grow smaller, I suppose.' So she began very cautiously: 'But I don't remember where.' 'Well, it must make me grow larger, I can find it.' And she kept tossing the baby at her.",
			"address": {
				"street": "Eleakierros 3",
				"streetName": "Nyk\u00e4nenhaka",
				"buildingNumber": "25",
				"city": "Esavesi",
				"zipcode": "15662",
				"country": "Brasilia",
				"county_code": "MT",
				"latitude": -49.218384,
				"longitude": 28.321802
			},
			"website": "http:\/\/heimola.net",
			"pictures": ["http:\/\/placeimg.com\/640\/480\/people", "http:\/\/placeimg.com\/640\/480\/people", "http:\/\/placeimg.com\/640\/480\/people"]

		},
		{
			"firstname": "Miika",
			"lastname": "Ainola",
			"email": "tatu.kumpulainen@ruutti.com",
			"phone": "+1369048271407",
			"birthday": "1992-10-30",
			"sexualPreference":"Hetero",
			"gender": "male",
			"biography": "No, there were a Duck and a fan! Quick, now!' And Alice was not otherwise than what it was perfectly round, she came up to the Mock Turtle, and to wonder what they'll do next! As for pulling me out.",
			"address": {
				"street": "Halmekaari 956 066",
				"streetName": "Leevikaari",
				"buildingNumber": "41",
				"city": "Uus-Juhoj\u00e4rvi",
				"zipcode": "38519",
				"country": "Andorra",
				"county_code": "TD",
				"latitude": -32.616359,
				"longitude": -143.667869
			},
			"website": "http:\/\/laine.info",
			"pictures": ["http:\/\/placeimg.com\/640\/480\/people", "http:\/\/placeimg.com\/640\/480\/people", "http:\/\/placeimg.com\/640\/480\/people"]

		},
		{
			"firstname": "Samuel",
			"lastname": "Luukkonen",
			"email": "tukiainen.mirva@jippii.fi",
			"phone": "+6555387908534",
			"birthday": "1948-05-20",
			"sexualPreference":"Hetero",
			"gender": "male",
			"biography": "Knave, 'I didn't mean it!' pleaded poor Alice. 'But you're so easily offended!' 'You'll get used up.' 'But what did the Dormouse began in a tone of great curiosity. 'Soles and eels, of course,' the.",
			"address": {
				"street": "Rinnepolku 308",
				"streetName": "Arponenkaarto",
				"buildingNumber": "032",
				"city": "Uusi-Elias",
				"zipcode": "84606",
				"country": "Honduras",
				"county_code": "GT",
				"latitude": -50.816026,
				"longitude": 3.706881
			},
			"website": "http:\/\/rasanen.com",
			"pictures": ["http:\/\/placeimg.com\/640\/480\/people", "http:\/\/placeimg.com\/640\/480\/people", "http:\/\/placeimg.com\/640\/480\/people"]

		},
		{
			"firstname": "Jore",
			"lastname": "Raatikainen",
			"email": "elise.halme@jippii.fi",
			"phone": "+1402690750201",
			"birthday": "2006-06-04",
			"sexualPreference":"Asexual",
			"gender": "male",
			"biography": "Mock Turtle's Story 'You can't think how glad I am in the book,' said the Queen, but she got back to the other, looking uneasily at the Cat's head began fading away the moment she quite forgot how.",
			"address": {
				"street": "Hypp\u00f6l\u00e4polku 087 269",
				"streetName": "Ristil\u00e4tie",
				"buildingNumber": "5",
				"city": "Iljavesi",
				"zipcode": "13508",
				"country": "Saint Vincent ja Grenadiinit",
				"county_code": "FR",
				"latitude": -71.983436,
				"longitude": -58.865238
			},
			"website": "http:\/\/helmel.com",
			"pictures": ["http:\/\/placeimg.com\/640\/480\/people", "http:\/\/placeimg.com\/640\/480\/people", "http:\/\/placeimg.com\/640\/480\/people"]

		},
		{
			"firstname": "Eva",
			"lastname": "Haapakorpi",
			"email": "miina.hyyppa@hotmail.com",
			"phone": "+9501151103224",
			"birthday": "1933-07-23",
			"sexualPreference":"Pansexual",
			"gender": "female",
			"biography": "This question the Dodo solemnly presented the thimble, looking as solemn as she could not possibly reach it: she could remember them, all these changes are! I'm never sure what I'm going to say,'.",
			"address": {
				"street": "Juuliapolku 6631",
				"streetName": "Anitahaka",
				"buildingNumber": "7875",
				"city": "Etel\u00e4-Elina",
				"zipcode": "25297",
				"country": "Ecuador",
				"county_code": "SX",
				"latitude": -25.596348,
				"longitude": 147.254876
			},
			"website": "http:\/\/puupera.com",
			"pictures": ["http:\/\/placeimg.com\/640\/480\/people", "http:\/\/placeimg.com\/640\/480\/people", "http:\/\/placeimg.com\/640\/480\/people"]
			
		},
		{
			"firstname": "Reetta",
			"lastname": "Hento",
			"email": "clara.koirala@hanhinen.com",
			"phone": "+2281633348165",
			"birthday": "1953-11-26",
			"sexualPreference":"Pansexual",
			"gender": "female",
			"biography": "Mouse, who was trembling down to look for her, and the moment they saw Alice coming. 'There's PLENTY of room!' said Alice angrily. 'It wasn't very civil of you to sit down without being invited,'.",
			"address": {
				"street": "Hakkit\u00f6yry 6",
				"streetName": "Inkakaarre",
				"buildingNumber": "5",
				"city": "It\u00e4-Velipudas",
				"zipcode": "78940",
				"country": "Armenia",
				"county_code": "CF",
				"latitude": 27.656471,
				"longitude": 153.346405
			},
			"website": "http:\/\/litmanen.com",
			"pictures": ["http:\/\/placeimg.com\/640\/480\/people", "http:\/\/placeimg.com\/640\/480\/people", "http:\/\/placeimg.com\/640\/480\/people"]
			
		},
		{
			"firstname": "Kimi",
			"lastname": "H\u00e4m\u00e4l\u00e4inen",
			"email": "eramaja.tiina@yahoo.com",
			"phone": "+3267433597543",
			"birthday": "2017-12-20",
			"sexualPreference":"Hetero",
			"gender": "female",
			"biography": "There was a real nose; also its eyes again, to see if she meant to take MORE than nothing.' 'Nobody asked YOUR opinion,' said Alice. 'Nothing WHATEVER?' persisted the King. (The jury all brightened.",
			"address": {
				"street": "Luukast\u00f6yry 74",
				"streetName": "Lummekatu",
				"buildingNumber": "1374",
				"city": "Mettekyl\u00e4",
				"zipcode": "43500",
				"country": "Marokko",
				"county_code": "IR",
				"latitude": -82.614458,
				"longitude": -147.531658
			},
			"website": "http:\/\/kynsijarvi.com",
			"pictures": ["http:\/\/placeimg.com\/640\/480\/people", "http:\/\/placeimg.com\/640\/480\/people", "http:\/\/placeimg.com\/640\/480\/people"]
			
		},
		{
			"firstname": "Anssi",
			"lastname": "Ristil\u00e4",
			"email": "mimosa68@hotmail.com",
			"phone": "+7043877115274",
			"birthday": "1966-12-21",
			"sexualPreference":"Hetero",
			"gender": "male",
			"biography": "Alice. 'Who's making personal remarks now?' the Hatter said, tossing his head mournfully. 'Not I!' said the March Hare. 'Then it wasn't very civil of you to get out again. The rabbit-hole went.",
			"address": {
				"street": "Emmakaarre 83",
				"streetName": "Tuomistosilta",
				"buildingNumber": "4600",
				"city": "Matleenasalmi",
				"zipcode": "94892",
				"country": "Thaimaa",
				"county_code": "BB",
				"latitude": 48.99856,
				"longitude": -43.366988
			},
			"website": "http:\/\/kiiski.org",
			"pictures": ["http:\/\/placeimg.com\/640\/480\/people", "http:\/\/placeimg.com\/640\/480\/people", "http:\/\/placeimg.com\/640\/480\/people"]
			
		},
		{
			"firstname": "Pertti",
			"lastname": "Niemist\u00f6",
			"email": "reeta.koirala@aalto.com",
			"phone": "+8988660952746",
			"birthday": "2008-02-19",
			"sexualPreference":"Hetero",
			"gender": "male",
			"biography": "Queen,' and she swam lazily about in the shade: however, the moment she quite forgot how to begin.' For, you see, because some of them didn't know how to spell 'stupid,' and that he shook both his.",
			"address": {
				"street": "Emmaliinakuja 4 595",
				"streetName": "Alaj\u00e4rvipolku",
				"buildingNumber": "229",
				"city": "It\u00e4-Lassi",
				"zipcode": "92787",
				"country": "Qatar",
				"county_code": "CC",
				"latitude": -62.807009,
				"longitude": -109.058204
			},
			"website": "http:\/\/evila.com",
			"pictures": ["http:\/\/placeimg.com\/640\/480\/people", "http:\/\/placeimg.com\/640\/480\/people", "http:\/\/placeimg.com\/640\/480\/people"]
			
		},
		{
			"firstname": "Olivia",
			"lastname": "Hanhinen",
			"email": "teppo60@hongisto.fi",
			"phone": "+3501490113995",
			"birthday": "1971-09-18",
			"sexualPreference":"Hetero",
			"gender": "female",
			"biography": "ARE a simpleton.' Alice did not dare to laugh; and, as there was not otherwise than what you would seem to have the experiment tried. 'Very true,' said the young man said, 'And your hair has become.",
			"address": {
				"street": "Kristiankaarto 0",
				"streetName": "Jenikatie",
				"buildingNumber": "0",
				"city": "It\u00e4-Jadessa",
				"zipcode": "85614",
				"country": "Bahrain",
				"county_code": "BO",
				"latitude": -63.081293,
				"longitude": -16.684731
			},
			"website": "http:\/\/nykanen.com",
			"pictures": ["http:\/\/placeimg.com\/640\/480\/people", "http:\/\/placeimg.com\/640\/480\/people", "http:\/\/placeimg.com\/640\/480\/people"]
			
		},
		{
			"firstname": "Fiona",
			"lastname": "Lehtim\u00e4ki",
			"email": "juho.ristila@varjus.com",
			"phone": "+4303385865229",
			"birthday": "1994-10-01",
			"sexualPreference":"Hetero",
			"gender": "female",
			"biography": "So they went on in these words: 'Yes, we went to work very diligently to write this down on their slates, when the White Rabbit blew three blasts on the twelfth?' Alice went on, 'What HAVE you been.",
			"address": {
				"street": "Jennarinne 15",
				"streetName": "Sirkesalokierros",
				"buildingNumber": "54",
				"city": "Eelissaari",
				"zipcode": "83849",
				"country": "Kap Verde",
				"county_code": "ET",
				"latitude": -18.443187,
				"longitude": -15.189366
			},
			"website": "http:\/\/heiskanen.biz",
			"pictures": ["http:\/\/placeimg.com\/640\/480\/people", "http:\/\/placeimg.com\/640\/480\/people", "http:\/\/placeimg.com\/640\/480\/people"]

		},
		{
			"firstname": "Riikka",
			"lastname": "Arnio",
			"email": "wsoini@hakamies.org",
			"phone": "+5286855788088",
			"birthday": "1974-07-22",
			"sexualPreference":"Hetero",
			"gender": "female",
			"biography": "THE KING AND QUEEN OF HEARTS. Alice was not much surprised at this, but at the flowers and the turtles all advance! They are waiting on the glass table and the whole pack of cards!' At this moment.",
			"address": {
				"street": "Aholasilta 62",
				"streetName": "Mujunenrinne",
				"buildingNumber": "7",
				"city": "Reetasaari",
				"zipcode": "90863",
				"country": "Kypros",
				"county_code": "FO",
				"latitude": -62.042717,
				"longitude": -77.35996
			},
			"website": "http:\/\/jauhiainen.biz",
			"pictures": ["http:\/\/placeimg.com\/640\/480\/people", "http:\/\/placeimg.com\/640\/480\/people", "http:\/\/placeimg.com\/640\/480\/people"]
			
		},
		{
			"firstname": "Patrik",
			"lastname": "Hammas",
			"email": "matti.koirala@jippii.fi",
			"phone": "+2195699118825",
			"birthday": "1943-12-24",
			"sexualPreference":"Bi",
			"gender": "male",
			"biography": "Alice hastily; 'but I'm not myself, you see.' 'I don't see any wine,' she remarked. 'There isn't any,' said the March Hare took the regular course.' 'What was that?' inquired Alice. 'Reeling and.",
			"address": {
				"street": "Iidakaarto 86 934",
				"streetName": "Hallapurorinne",
				"buildingNumber": "8951",
				"city": "Uus-Amandaharju",
				"zipcode": "29562",
				"country": "Ruanda",
				"county_code": "SB",
				"latitude": -49.874079,
				"longitude": -82.44924
			},
			"website": "http:\/\/ammala.info",
			"pictures": ["http:\/\/placeimg.com\/640\/480\/people", "http:\/\/placeimg.com\/640\/480\/people", "http:\/\/placeimg.com\/640\/480\/people"]
			
		},
		{
			"firstname": "Lila",
			"lastname": "Akkala",
			"email": "masanen.kaija@markus.biz",
			"phone": "+1561415300894",
			"birthday": "1961-04-03",
			"gender": "female",
			"biography": "YOU, and no room to grow to my right size: the next moment she quite forgot how to get through the neighbouring pool--she could hear the name of the song, she kept fanning herself all the unjust.",
			"address": {
				"street": "Arosuokierros 838",
				"streetName": "Katainent\u00f6yry",
				"buildingNumber": "2",
				"city": "Iidaj\u00e4rvi",
				"zipcode": "17260",
				"country": "Filippiinit",
				"county_code": "SZ",
				"latitude": -12.659828,
				"longitude": -13.018937
			},
			"website": "http:\/\/vuorinen.info",
			"pictures": ["http:\/\/placeimg.com\/640\/480\/people", "http:\/\/placeimg.com\/640\/480\/people", "http:\/\/placeimg.com\/640\/480\/people"]
			
		},
		{
			"firstname": "Tuukka",
			"lastname": "Helstel",
			"email": "oona.erola@eskela.info",
			"phone": "+9290024190573",
			"birthday": "2006-07-19",
			"sexualPreference":"Hetero",
			"gender": "male",
			"biography": "When the pie was all dark overhead; before her was another puzzling question; and as it happens; and if the Queen was in March.' As she said this, she looked up, but it makes rather a handsome pig.",
			"address": {
				"street": "Lehtim\u00e4kikatu 499 417",
				"streetName": "Lehm\u00e4l\u00e4rinne",
				"buildingNumber": "9",
				"city": "Juhovesi",
				"zipcode": "71726",
				"country": "Laos",
				"county_code": "LB",
				"latitude": -58.384265,
				"longitude": -84.717326
			},
			"website": "http:\/\/saanila.com",
			"pictures": ["http:\/\/placeimg.com\/640\/480\/people", "http:\/\/placeimg.com\/640\/480\/people", "http:\/\/placeimg.com\/640\/480\/people"]
			
		},
		{
			"firstname": "Touko",
			"lastname": "Pirttikangas",
			"email": "pyykkonen.mirva@gmail.com",
			"phone": "+8457970873146",
			"birthday": "1994-11-11",
			"sexualPreference":"Hetero",
			"gender": "male",
			"biography": "I can kick a little!' She drew her foot as far as they lay on the door began sneezing all at once. The Dormouse again took a great deal of thought, and looked anxiously at the house, \"Let us both go.",
			"address": {
				"street": "Kantolat\u00f6yry 298 336",
				"streetName": "Noorakaari",
				"buildingNumber": "9815",
				"city": "Maijapudas",
				"zipcode": "36681",
				"country": "Mali",
				"county_code": "NO",
				"latitude": 42.351521,
				"longitude": 110.363754
			},
			"website": "http:\/\/lehtimaki.com",
			"pictures": ["http:\/\/placeimg.com\/640\/480\/people", "http:\/\/placeimg.com\/640\/480\/people", "http:\/\/placeimg.com\/640\/480\/people"]
			
		},
		{
			"firstname": "Esa",
			"lastname": "Ramu",
			"email": "eveliina32@luukku.com",
			"phone": "+5689894751468",
			"birthday": "2002-07-12",
			"sexualPreference":"Hetero",
			"gender": "female",
			"biography": "Alice again, for she had never done such a very grave voice, 'until all the jelly-fish out of that is--\"The more there is of finding morals in things!' Alice began to get through the little creature.",
			"address": {
				"street": "Jusukatu 02 924",
				"streetName": "Vilkkulakaarto",
				"buildingNumber": "0",
				"city": "Pohjois-Dani",
				"zipcode": "51407",
				"country": "Costa Rica",
				"county_code": "CG",
				"latitude": 36.64676,
				"longitude": -8.165827
			},
			"website": "http:\/\/jurvanen.org",
			"pictures": ["http:\/\/placeimg.com\/640\/480\/people", "http:\/\/placeimg.com\/640\/480\/people", "http:\/\/placeimg.com\/640\/480\/people"]
			
		},
		{
			"firstname": "Jadessa",
			"lastname": "Isoluoma",
			"email": "samu.nykanen@gmail.com",
			"phone": "+9496578175903",
			"birthday": "1948-09-27",
			"sexualPreference":"Hetero",
			"gender": "female",
			"biography": "Gryphon. 'I've forgotten the little golden key, and when she had never seen such a neck as that! No, no! You're a serpent; and there's no meaning in it, 'and what is the reason is--' here the Mock.",
			"address": {
				"street": "Sannakatu 50",
				"streetName": "Nieminenkulma",
				"buildingNumber": "258",
				"city": "Hervantaniemi",
				"zipcode": "84534",
				"country": "Marshallinsaaret",
				"county_code": "NU",
				"latitude": 21.090338,
				"longitude": 141.240583
			},
			"website": "http:\/\/wirtanen.com",
			"pictures": ["http:\/\/placeimg.com\/640\/480\/people", "http:\/\/placeimg.com\/640\/480\/people", "http:\/\/placeimg.com\/640\/480\/people"]
			
		},
		{
			"firstname": "Sisu",
			"lastname": "Haavisto",
			"email": "taavila.osmo@jippii.fi",
			"phone": "+1723281766116",
			"birthday": "1964-01-20",
			"sexualPreference":"Hetero",
			"gender": "male",
			"biography": "Mock Turtle. 'No, no! The adventures first,' said the Gryphon went on, turning to the shore, and then raised himself upon tiptoe, put his shoes off. 'Give your evidence,' the King exclaimed, turning.",
			"address": {
				"street": "Jauhiainenkaari 534",
				"streetName": "Tiilikainenkulma",
				"buildingNumber": "5037",
				"city": "Uusi-Juha",
				"zipcode": "49439",
				"country": "Jamaika",
				"county_code": "TJ",
				"latitude": 45.616394,
				"longitude": 98.254104
			},
			"website": "http:\/\/vuokko.com",
			"pictures": ["http:\/\/placeimg.com\/640\/480\/people", "http:\/\/placeimg.com\/640\/480\/people", "http:\/\/placeimg.com\/640\/480\/people"]
			
		},
		{
			"firstname": "Aune",
			"lastname": "Kallio",
			"email": "harri.ojamaki@hotmail.com",
			"phone": "+3752572299028",
			"birthday": "1956-09-19",
			"sexualPreference":"Hetero",
			"gender": "male",
			"biography": "Caterpillar. 'Well, I've tried hedges,' the Pigeon the opportunity of saying to herself, 'after such a tiny golden key, and unlocking the door of which was full of soup. 'There's certainly too much.",
			"address": {
				"street": "Johannakatu 8",
				"streetName": "Marilakatu",
				"buildingNumber": "6687",
				"city": "Janikam\u00e4ki",
				"zipcode": "81101",
				"country": "Tad\u1e91ikistan",
				"county_code": "SD",
				"latitude": 82.996677,
				"longitude": 177.321503
			},
			"website": "http:\/\/vesuri.info",
			"pictures": ["http:\/\/placeimg.com\/640\/480\/people", "http:\/\/placeimg.com\/640\/480\/people", "http:\/\/placeimg.com\/640\/480\/people"]
			
		},
		{
			"firstname": "Niko",
			"lastname": "Niukkanen",
			"email": "hilppa26@jippii.fi",
			"phone": "+2855157600189",
			"birthday": "2020-08-15",
			"sexualPreference":"Hetero",
			"gender": "male",
			"biography": "For, you see, so many lessons to learn! No, I've made up my mind about it; if I'm not the smallest notice of her going, though she felt sure she would get up and down looking for them, and.",
			"address": {
				"street": "Silvennoinenpolku 14 814",
				"streetName": "Maiarinne",
				"buildingNumber": "101",
				"city": "Uus-Touko",
				"zipcode": "14590",
				"country": "Thaimaa",
				"county_code": "LT",
				"latitude": 28.556296,
				"longitude": 76.078708
			},
			"website": "http:\/\/myllymaki.fi",
			"pictures": ["http:\/\/placeimg.com\/640\/480\/people", "http:\/\/placeimg.com\/640\/480\/people", "http:\/\/placeimg.com\/640\/480\/people"]
			
		},
		{
			"firstname": "Onni",
			"lastname": "Taipale",
			"email": "riku.vahala@litmanen.fi",
			"phone": "+6428644380305",
			"birthday": "1948-05-01",
			"sexualPreference":"Hetero",
			"gender": "male",
			"biography": "I've had such a simple question,' added the Dormouse, after thinking a minute or two, it was getting very sleepy; 'and they all spoke at once, while all the children she knew, who might do something.",
			"address": {
				"street": "Auranenkaari 9156",
				"streetName": "Aliinasilta",
				"buildingNumber": "9",
				"city": "L\u00e4nsi-Leokoski",
				"zipcode": "43957",
				"country": "Marshallinsaaret",
				"county_code": "RU",
				"latitude": -70.581818,
				"longitude": -93.590771
			},
			"website": "http:\/\/mannonen.com",
			"pictures": ["http:\/\/placeimg.com\/640\/480\/people", "http:\/\/placeimg.com\/640\/480\/people", "http:\/\/placeimg.com\/640\/480\/people"]
			
		},
		{
			"firstname": "Veera",
			"lastname": "V\u00e4yrynen",
			"email": "khelppolainen@aitio.org",
			"phone": "+8684883671328",
			"birthday": "1987-10-18",
			"sexualPreference":"Hetero",
			"gender": "female",
			"biography": "Alice quietly said, just as the Dormouse shook itself, and began talking to herself, for this curious child was very provoking to find that she had never done such a capital one for catching.",
			"address": {
				"street": "Parkkonenkaarto 93 712",
				"streetName": "Saarelasilta",
				"buildingNumber": "2",
				"city": "Ennikapudas",
				"zipcode": "24844",
				"country": "Belize",
				"county_code": "MG",
				"latitude": -42.844543,
				"longitude": 43.558552
			},
			"website": "http:\/\/lukkari.net",
			"pictures": ["http:\/\/placeimg.com\/640\/480\/people", "http:\/\/placeimg.com\/640\/480\/people", "http:\/\/placeimg.com\/640\/480\/people"]
			
		},
		{
			"firstname": "Tatu",
			"lastname": "Sikala",
			"email": "bkoirala@haapkyla.com",
			"phone": "+4616726254266",
			"birthday": "1933-04-01",
			"sexualPreference":"Hetero",
			"gender": "male",
			"biography": "There could be beheaded, and that makes them so often, of course was, how to spell 'stupid,' and that if you want to see if there were a Duck and a large canvas bag, which tied up at this.",
			"address": {
				"street": "Haikalatie 421 901",
				"streetName": "Pakkalakaari",
				"buildingNumber": "4897",
				"city": "Anttinensaari",
				"zipcode": "75873",
				"country": "Kuuba",
				"county_code": "VC",
				"latitude": 41.701586,
				"longitude": -54.856674
			},
			"website": "http:\/\/melasniemi.fi",
			"pictures": ["http:\/\/placeimg.com\/640\/480\/people", "http:\/\/placeimg.com\/640\/480\/people", "http:\/\/placeimg.com\/640\/480\/people"]
			
		},
		{
			"firstname": "Eveliina",
			"lastname": "\u00d6ysti",
			"email": "krista92@nokkonen.com",
			"phone": "+5402197075115",
			"birthday": "1959-12-09",
			"sexualPreference":"Hetero",
			"gender": "female",
			"biography": "The great question certainly was, what? Alice looked at her, and said, 'So you did, old fellow!' said the Gryphon. 'Turn a somersault in the house, \"Let us both go to law: I will prosecute.",
			"address": {
				"street": "Markusrinne 9",
				"streetName": "Syd\u00e4nm\u00e4kikaarto",
				"buildingNumber": "972",
				"city": "Etel\u00e4-Mari",
				"zipcode": "63109",
				"country": "Moldova",
				"county_code": "PF",
				"latitude": 4.722597,
				"longitude": 95.473942
			},
			"website": "http:\/\/hovi.com",
			"pictures": ["http:\/\/placeimg.com\/640\/480\/people", "http:\/\/placeimg.com\/640\/480\/people", "http:\/\/placeimg.com\/640\/480\/people"]
			
		},
		{
			"firstname": "Jadessa",
			"lastname": "Kalvo",
			"email": "ukoivuniemi@vahvanen.com",
			"phone": "+7909349759889",
			"birthday": "1965-05-17",
			"sexualPreference":"Hetero",
			"gender": "female",
			"biography": "LESS,' said the Gryphon. 'The reason is,' said the Hatter. This piece of rudeness was more and more faintly came, carried on the door began sneezing all at once. The Dormouse had closed its eyes.",
			"address": {
				"street": "Attesilta 0",
				"streetName": "Alapurokuja",
				"buildingNumber": "45",
				"city": "Roopesalmi",
				"zipcode": "61681",
				"country": "Grenada",
				"county_code": "FJ",
				"latitude": -21.73239,
				"longitude": -44.438756
			},
			"website": "http:\/\/ryysylainen.com",
			"pictures": ["http:\/\/placeimg.com\/640\/480\/people", "http:\/\/placeimg.com\/640\/480\/people", "http:\/\/placeimg.com\/640\/480\/people"]
			
		},
		{
			"firstname": "Matias",
			"lastname": "Vesuri",
			"email": "aenola@luukku.com",
			"phone": "+2758545628872",
			"birthday": "1954-03-17",
			"sexualPreference":"Hetero",
			"gender": "male",
			"biography": "Grammar, 'A mouse--of a mouse--to a mouse--a mouse--O mouse!') The Mouse did not at all know whether it was certainly English. 'I don't see,' said the Gryphon. 'We can do without lobsters, you know.",
			"address": {
				"street": "Eljaskaari 9",
				"streetName": "Halinenkulma",
				"buildingNumber": "8689",
				"city": "L\u00e4nsi-Jonnasalmi",
				"zipcode": "11945",
				"country": "Moldova",
				"county_code": "IR",
				"latitude": 63.690828,
				"longitude": 105.021081
			},
			"website": "http:\/\/auvinen.net",
			"pictures": ["http:\/\/placeimg.com\/640\/480\/people", "http:\/\/placeimg.com\/640\/480\/people", "http:\/\/placeimg.com\/640\/480\/people"]
			
		},
		{
			"firstname": "Veli",
			"lastname": "Tuppurainen",
			"email": "paavo57@jippii.fi",
			"phone": "+2931207934185",
			"birthday": "1949-05-09",
			"sexualPreference":"Hetero",
			"gender": "male",
			"biography": "And with that she was now, and she went out, but it was over at last, and managed to swallow a morsel of the busy farm-yard--while the lowing of the party sat silent for a minute or two, looking for.",
			"address": {
				"street": "Isoluomasilta 5",
				"streetName": "Heidikaari",
				"buildingNumber": "67",
				"city": "Nuuttikyl\u00e4",
				"zipcode": "23865",
				"country": "Slovakia",
				"county_code": "SZ",
				"latitude": -42.033785,
				"longitude": 18.828641
			},
			"website": "http:\/\/kivisto.com",
			"pictures": ["http:\/\/placeimg.com\/640\/480\/people", "http:\/\/placeimg.com\/640\/480\/people", "http:\/\/placeimg.com\/640\/480\/people"]
			
		},
		{
			"firstname": "Ari",
			"lastname": "M\u00e4kel\u00e4",
			"email": "jonna94@krekela.info",
			"phone": "+9005960711215",
			"birthday": "1955-07-22",
			"sexualPreference":"Hetero",
			"gender": "male",
			"biography": "Alice thought she might as well as if it thought that she let the Dormouse shall!' they both bowed low, and their slates and pencils had been would have done that?' she thought. 'But everything's.",
			"address": {
				"street": "Eetuhaka 296 037",
				"streetName": "Ruusulakaarto",
				"buildingNumber": "615",
				"city": "Uusi-Celina",
				"zipcode": "98666",
				"country": "Valko-Ven\u00e4j\u00e4",
				"county_code": "MZ",
				"latitude": 10.630266,
				"longitude": -176.936607
			},
			"website": "http:\/\/pahajoki.com",
			"pictures": ["http:\/\/placeimg.com\/640\/480\/people", "http:\/\/placeimg.com\/640\/480\/people", "http:\/\/placeimg.com\/640\/480\/people"]
			
		},
		{
			"firstname": "Kaisla",
			"lastname": "Wirtanen",
			"email": "okeskinen@hotmail.com",
			"phone": "+2720694558609",
			"birthday": "1933-12-30",
			"sexualPreference":"Hetero",
			"gender": "female",
			"biography": "Mouse gave a little more conversation with her head!' Alice glanced rather anxiously at the Caterpillar's making such a hurry that she wasn't a really good school,' said the King, the Queen, who was.",
			"address": {
				"street": "Jannekulma 5",
				"streetName": "Servot\u00f6yry",
				"buildingNumber": "9",
				"city": "Uusi-Taika",
				"zipcode": "42385",
				"country": "Bhutan",
				"county_code": "BG",
				"latitude": -70.607298,
				"longitude": -137.848938
			},
			"website": "http:\/\/jokelainen.com",
			"pictures": ["http:\/\/placeimg.com\/640\/480\/people", "http:\/\/placeimg.com\/640\/480\/people", "http:\/\/placeimg.com\/640\/480\/people"]
			
		},
		{
			"firstname": "Jesper",
			"lastname": "Lehtim\u00e4ki",
			"email": "kangassalo.anniina@loiri.com",
			"phone": "+2787703222960",
			"birthday": "1997-07-26",
			"sexualPreference":"Hetero",
			"gender": "male",
			"biography": "I wonder what was going on, as she spoke--fancy CURTSEYING as you're falling through the door, staring stupidly up into a graceful zigzag, and was going to turn round on its axis--' 'Talking of.",
			"address": {
				"street": "Reinikkarinne 77",
				"streetName": "Viljokuja",
				"buildingNumber": "3",
				"city": "Uus-Janneniemi",
				"zipcode": "32543",
				"country": "Burkina Faso",
				"county_code": "CM",
				"latitude": 41.519515,
				"longitude": -74.458614
			},
			"website": "http:\/\/kokkonen.net",
			"pictures": ["http:\/\/placeimg.com\/640\/480\/people", "http:\/\/placeimg.com\/640\/480\/people", "http:\/\/placeimg.com\/640\/480\/people"]
			
		},
		{
			"firstname": "Outi",
			"lastname": "Ikola",
			"email": "helovirta.henniina@tynkkynen.org",
			"phone": "+2499954066189",
			"birthday": "1983-11-02",
			"sexualPreference":"Hetero",
			"gender": "female",
			"biography": "Footman, 'and that for two reasons. First, because I'm on the door with his head!' she said, 'and see whether it's marked \"poison\" or not'; for she was quite pleased to find that she knew she had.",
			"address": {
				"street": "M\u00e4ntyl\u00e4kaarre 236",
				"streetName": "Jonnakaarto",
				"buildingNumber": "13",
				"city": "It\u00e4-Aappo",
				"zipcode": "43945",
				"country": "Togo",
				"county_code": "LR",
				"latitude": -71.640213,
				"longitude": -175.174039
			},
			"website": "http:\/\/saloranta.com",
			"pictures": ["http:\/\/placeimg.com\/640\/480\/people", "http:\/\/placeimg.com\/640\/480\/people", "http:\/\/placeimg.com\/640\/480\/people"]
			
		},
		{
			"firstname": "Maija",
			"lastname": "Nieminen",
			"email": "emmaliina40@liimatainen.net",
			"phone": "+3948416613230",
			"birthday": "1976-06-02",
			"sexualPreference":"Hetero",
			"gender": "female",
			"biography": "There was no more to come, so she began nibbling at the picture.) 'Up, lazy thing!' said Alice, very much of a feather flock together.\"' 'Only mustard isn't a letter, after all: it's a very curious.",
			"address": {
				"street": "Aunet\u00f6yry 328",
				"streetName": "Patrikkuja",
				"buildingNumber": "2003",
				"city": "Komulainenkyl\u00e4",
				"zipcode": "77651",
				"country": "Botswana",
				"county_code": "TM",
				"latitude": -72.220351,
				"longitude": -154.063138
			},
			"website": "http:\/\/pesola.com",
			"pictures": ["http:\/\/placeimg.com\/640\/480\/people", "http:\/\/placeimg.com\/640\/480\/people", "http:\/\/placeimg.com\/640\/480\/people"]
			
		},
		{
			"firstname": "Briitta",
			"lastname": "Anttila",
			"email": "paulus10@tyrninen.net",
			"phone": "+1700687075882",
			"birthday": "1981-11-07",
			"sexualPreference":"Hetero",
			"gender": "male",
			"biography": "I suppose you'll be asleep again before it's done.' 'Once upon a little way off, panting, with its legs hanging down, but generally, just as well to say \"HOW DOTH THE LITTLE BUSY BEE,\" but it is.'.",
			"address": {
				"street": "Sarikatu 00 518",
				"streetName": "Harjunp\u00e4\u00e4kaari",
				"buildingNumber": "7",
				"city": "Etel\u00e4-Eelisaari",
				"zipcode": "64484",
				"country": "Luxemburg",
				"county_code": "SE",
				"latitude": -52.343098,
				"longitude": -112.406344
			},
			"website": "http:\/\/turpeinen.biz",
			"pictures": ["http:\/\/placeimg.com\/640\/480\/people", "http:\/\/placeimg.com\/640\/480\/people", "http:\/\/placeimg.com\/640\/480\/people"]
			
		},
		{
			"firstname": "Jadessa",
			"lastname": "Merel\u00e4",
			"email": "myrjanen@aakula.com",
			"phone": "+4520951452488",
			"birthday": "1982-06-14",
			"sexualPreference":"Hetero",
			"gender": "female",
			"biography": "I ought to speak, and no room to grow to my boy, I beat him when he pleases!' CHORUS. 'Wow! wow! wow!' While the Panther were sharing a pie--' [later editions continued as follows When the pie was.",
			"address": {
				"street": "Eveliinasilta 6 315",
				"streetName": "Innakaari",
				"buildingNumber": "8866",
				"city": "L\u00e4nsi-Mirellapudas",
				"zipcode": "67379",
				"country": "Costa Rica",
				"county_code": "HK",
				"latitude": 27.230781,
				"longitude": -103.454871
			},
			"website": "http:\/\/autio.biz",
			"pictures": ["http:\/\/placeimg.com\/640\/480\/people", "http:\/\/placeimg.com\/640\/480\/people", "http:\/\/placeimg.com\/640\/480\/people"]
			
		},
		{
			"firstname": "Jenika",
			"lastname": "Utriainen",
			"email": "juvanen.anna@davidsainen.com",
			"phone": "+3318208225074",
			"birthday": "1942-11-11",
			"sexualPreference":"Hetero",
			"gender": "female",
			"biography": "March Hare said to herself what such an extraordinary ways of living would be quite as safe to stay in here any longer!' She waited for a minute or two, looking for it, you may stand down,'.",
			"address": {
				"street": "Ervolarinne 99",
				"streetName": "Pyryrinne",
				"buildingNumber": "85",
				"city": "Kallem\u00e4ki",
				"zipcode": "67338",
				"country": "Panama",
				"county_code": "IS",
				"latitude": -2.535001,
				"longitude": -85.265997
			},
			"website": "http:\/\/taavila.org",
			"pictures": ["http:\/\/placeimg.com\/640\/480\/people", "http:\/\/placeimg.com\/640\/480\/people", "http:\/\/placeimg.com\/640\/480\/people"]
			
		},
		{
			"firstname": "Pertti",
			"lastname": "Koivula",
			"email": "pasi.huovinen@jippii.fi",
			"phone": "+6930760832506",
			"birthday": "1962-11-05",
			"sexualPreference":"Hetero",
			"gender": "male",
			"biography": "Ann! Mary Ann!' said the Hatter. 'It isn't directed at all,' said the youth, 'one would hardly suppose That your eye was as much use in talking to herself, as she spoke, but no result seemed to.",
			"address": {
				"street": "Ulvilarinne 3976",
				"streetName": "Sipil\u00e4kaarto",
				"buildingNumber": "6",
				"city": "L\u00e4nsi-Santtum\u00e4ki",
				"zipcode": "91968",
				"country": "Bahrain",
				"county_code": "RU",
				"latitude": 31.774874,
				"longitude": 119.988613
			},
			"website": "http:\/\/koivisto.com",
			"pictures": ["http:\/\/placeimg.com\/640\/480\/people", "http:\/\/placeimg.com\/640\/480\/people", "http:\/\/placeimg.com\/640\/480\/people"]
			
		},
		{
			"firstname": "Pihla",
			"lastname": "Tammisto",
			"email": "luca68@luukku.com",
			"phone": "+4944310241117",
			"birthday": "1933-07-01",
			"sexualPreference":"Hetero",
			"gender": "female",
			"biography": "Alice, in a very pretty dance,' said Alice in a low voice. 'Not at first, but, after watching it a minute or two to think about it, so she set to work at once without waiting for the end of the.",
			"address": {
				"street": "Christakuja 1 424",
				"streetName": "Samuelkaari",
				"buildingNumber": "3",
				"city": "Uusi-Matleenalampi",
				"zipcode": "23933",
				"country": "Slovakia",
				"county_code": "NR",
				"latitude": 8.745736,
				"longitude": -11.940366
			},
			"website": "http:\/\/ahomaa.com",
			"pictures": ["http:\/\/placeimg.com\/640\/480\/people", "http:\/\/placeimg.com\/640\/480\/people", "http:\/\/placeimg.com\/640\/480\/people"]
			
		},
		{
			"firstname": "Valtteri",
			"lastname": "Savolainen",
			"email": "aatto59@ryysylainen.com",
			"phone": "+1289417886554",
			"birthday": "1931-03-07",
			"sexualPreference":"Hetero",
			"gender": "male",
			"biography": "Alice looked up, and reduced the answer to it?' said the Gryphon. 'They can't have anything to put his shoes on. '--and just take his head contemptuously. 'I dare say there may be different,' said.",
			"address": {
				"street": "Oravalarinne 83",
				"streetName": "Viivirinne",
				"buildingNumber": "572",
				"city": "Uus-Ellaj\u00e4rvi",
				"zipcode": "65371",
				"country": "Belize",
				"county_code": "BH",
				"latitude": -86.323874,
				"longitude": 116.681897
			},
			"website": "http:\/\/nykanen.com",
			"pictures": ["http:\/\/placeimg.com\/640\/480\/people", "http:\/\/placeimg.com\/640\/480\/people", "http:\/\/placeimg.com\/640\/480\/people"]
			
		},
		{
			"firstname": "Jore",
			"lastname": "Huotari",
			"email": "antero21@yahoo.com",
			"phone": "+6669042979621",
			"birthday": "1931-09-28",
			"sexualPreference":"Hetero",
			"gender": "male",
			"biography": "Queen, but she ran across the garden, and I don't put my arm round your waist,' the Duchess said to herself, 'Now, what am I to get an opportunity of adding, 'You're looking for them, and the shrill.",
			"address": {
				"street": "Simotie 13 922",
				"streetName": "Urhot\u00f6yry",
				"buildingNumber": "7",
				"city": "Anniinakyl\u00e4",
				"zipcode": "95501",
				"country": "Burundi",
				"county_code": "LY",
				"latitude": 12.859567,
				"longitude": -173.828799
			},
			"website": "http:\/\/lappalainen.biz",
			"pictures": ["http:\/\/placeimg.com\/640\/480\/people", "http:\/\/placeimg.com\/640\/480\/people", "http:\/\/placeimg.com\/640\/480\/people"]
			
		},
		{
			"firstname": "Erkki",
			"lastname": "Malmi",
			"email": "jade.uusikari@tukiainen.info",
			"phone": "+7319106916869",
			"birthday": "2014-11-01",
			"sexualPreference":"Hetero",
			"gender": "male",
			"biography": "Alice; 'living at the White Rabbit blew three blasts on the glass table as before, 'and things are worse than ever,' thought the whole court was a queer-shaped little creature, and held out its arms.",
			"address": {
				"street": "Terokaari 85 194",
				"streetName": "Sirpakaarto",
				"buildingNumber": "2599",
				"city": "Hellgrenniemi",
				"zipcode": "09120",
				"country": "Kanada",
				"county_code": "NG",
				"latitude": 22.070245,
				"longitude": -101.038339
			},
			"website": "http:\/\/rapala.fi",
			"pictures": ["http:\/\/placeimg.com\/640\/480\/people", "http:\/\/placeimg.com\/640\/480\/people", "http:\/\/placeimg.com\/640\/480\/people"]
			
		},
		{
			"firstname": "Katja",
			"lastname": "Laaksonen",
			"email": "ninni.ojamaki@gmail.com",
			"phone": "+3714495593209",
			"birthday": "2016-02-04",
			"sexualPreference":"Hetero",
			"gender": "female",
			"biography": "The poor little feet, I wonder what you're talking about,' said Alice. 'And where HAVE my shoulders got to? And oh, I wish you wouldn't mind,' said Alice: 'she's so extremely--' Just then her head.",
			"address": {
				"street": "Jennarinne 4",
				"streetName": "Tatusilta",
				"buildingNumber": "287",
				"city": "Uus-Eelivesi",
				"zipcode": "71081",
				"country": "Puola",
				"county_code": "CN",
				"latitude": 41.732488,
				"longitude": 72.040352
			},
			"website": "http:\/\/ahonen.com",
			"pictures": ["http:\/\/placeimg.com\/640\/480\/people", "http:\/\/placeimg.com\/640\/480\/people", "http:\/\/placeimg.com\/640\/480\/people"]
			
		},
		{
			"firstname": "Helmiina",
			"lastname": "Lepom\u00e4ki",
			"email": "kannunen@hotmail.com",
			"phone": "+4219294731468",
			"birthday": "2008-04-09",
			"sexualPreference":"Hetero",
			"gender": "female",
			"biography": "HIS time of life. The King's argument was, that her idea of having the sentence first!' 'Hold your tongue!' added the Dormouse. 'Don't talk nonsense,' said Alice thoughtfully: 'but then--I shouldn't.",
			"address": {
				"street": "Lassipolku 03",
				"streetName": "Pakolarinne",
				"buildingNumber": "13",
				"city": "Uus-Jamij\u00e4rvi",
				"zipcode": "66193",
				"country": "Monaco",
				"county_code": "MD",
				"latitude": 57.610796,
				"longitude": 173.257306
			},
			"website": "http:\/\/kumpula.info",
			"pictures": ["http:\/\/placeimg.com\/640\/480\/people", "http:\/\/placeimg.com\/640\/480\/people", "http:\/\/placeimg.com\/640\/480\/people"]
			
		},
		{
			"firstname": "Johanna",
			"lastname": "Kurki",
			"email": "miina27@yahoo.com",
			"phone": "+1099932312701",
			"birthday": "1992-12-13",
			"sexualPreference":"Hetero",
			"gender": "female",
			"biography": "Bill had left off staring at the door-- Pray, what is the same when I was thinking I should think very likely true.) Down, down, down. There was a table set out under a tree in front of them, with.",
			"address": {
				"street": "Heikkil\u00e4katu 989",
				"streetName": "Oliiviakuja",
				"buildingNumber": "60",
				"city": "It\u00e4-Oona",
				"zipcode": "23670",
				"country": "Japani",
				"county_code": "ZM",
				"latitude": 44.811407,
				"longitude": -136.913287
			},
			"website": "http:\/\/kalvo.com",
			"pictures": ["http:\/\/placeimg.com\/640\/480\/people", "http:\/\/placeimg.com\/640\/480\/people", "http:\/\/placeimg.com\/640\/480\/people"]
			
		},
		{
			"firstname": "Iiro",
			"lastname": "Filppula",
			"email": "ojamaki.kimi@riihimaki.com",
			"phone": "+5871646229317",
			"birthday": "2001-02-11",
			"sexualPreference":"Asexual",
			"gender": "male",
			"biography": "Alice thought she had this fit) An obstacle that came between Him, and ourselves, and it. Don't let me hear the Rabbit actually TOOK A WATCH OUT OF ITS WAISTCOAT-POCKET, and looked at it, busily.",
			"address": {
				"street": "Kauppinenhaka 95 885",
				"streetName": "\u00c4n\u00e4kk\u00e4l\u00e4kaarto",
				"buildingNumber": "0",
				"city": "Ossij\u00e4rvi",
				"zipcode": "55796",
				"country": "Ukraina",
				"county_code": "MY",
				"latitude": 3.736809,
				"longitude": 17.543382
			},
			"website": "http:\/\/oja.info",
			"pictures": ["http:\/\/placeimg.com\/640\/480\/people", "http:\/\/placeimg.com\/640\/480\/people", "http:\/\/placeimg.com\/640\/480\/people"]
			
		},
		{
			"firstname": "Junnu",
			"lastname": "Karppinen",
			"email": "vjaakkonen@gmail.com",
			"phone": "+4322996852621",
			"birthday": "1932-06-13",
			"sexualPreference":"Bi",
			"gender": "male",
			"biography": "I get\" is the same thing as \"I eat what I could say if I shall be late!' (when she thought it must be kind to them,' thought Alice, and, after glaring at her as she ran; but the tops of the leaves.",
			"address": {
				"street": "Laaksokaarto 92",
				"streetName": "Viljakuja",
				"buildingNumber": "40",
				"city": "Pohjois-Jeminakyl\u00e4",
				"zipcode": "93655",
				"country": "Dominikaaninen tasavalta",
				"county_code": "VU",
				"latitude": 28.979709,
				"longitude": -82.197779
			},
			"website": "http:\/\/leppilampi.com",
			"pictures": ["http:\/\/placeimg.com\/640\/480\/people", "http:\/\/placeimg.com\/640\/480\/people", "http:\/\/placeimg.com\/640\/480\/people"]
			
		},
		{
			"firstname": "Nia",
			"lastname": "Tiainen",
			"email": "warnio@jippii.fi",
			"phone": "+3065231567525",
			"birthday": "2015-09-26",
			"sexualPreference":"Bi",
			"gender": "female",
			"biography": "I have to fly; and the procession came opposite to Alice, and she could do to come before that!' 'Call the first verse,' said the Duchess; 'and most of 'em do.' 'I don't believe it,' said Five, 'and.",
			"address": {
				"street": "Kannelmaarinne 4 521",
				"streetName": "Karukoskitie",
				"buildingNumber": "00",
				"city": "Alijokilampi",
				"zipcode": "97970",
				"country": "Kypros",
				"county_code": "RS",
				"latitude": -87.039275,
				"longitude": -122.498595
			},
			"website": "http:\/\/hakala.org",
			"pictures": ["http:\/\/placeimg.com\/640\/480\/people", "http:\/\/placeimg.com\/640\/480\/people", "http:\/\/placeimg.com\/640\/480\/people"]
			
		},
		{
			"firstname": "Luca",
			"lastname": "Santanen",
			"email": "aatu.komulainen@hakkarainen.info",
			"phone": "+7829358308331",
			"birthday": "2003-01-01",
			"sexualPreference":"Hetero",
			"gender": "male",
			"biography": "They had a door leading right into it. 'That's very curious.' 'It's all about as she had looked under it, and they repeated their arguments to her, one on each side, and opened their eyes and mouths.",
			"address": {
				"street": "Jussikaarto 3",
				"streetName": "Lampinenkuja",
				"buildingNumber": "21",
				"city": "Etel\u00e4-Juliajoki",
				"zipcode": "26668",
				"country": "Etel\u00e4-Sudan",
				"county_code": "SZ",
				"latitude": 18.084489,
				"longitude": -83.366892
			},
			"website": "http:\/\/vesuri.fi",
			"pictures": ["http:\/\/placeimg.com\/640\/480\/people", "http:\/\/placeimg.com\/640\/480\/people", "http:\/\/placeimg.com\/640\/480\/people"]
			
		},
		{
			"firstname": "Oliver",
			"lastname": "Haapakorpi",
			"email": "ninni60@gmail.com",
			"phone": "+8206003450144",
			"birthday": "1971-12-16",
			"sexualPreference":"Hetero",
			"gender": "male",
			"biography": "Alice, 'but I haven't had a head could be NO mistake about it: it was good practice to say it out loud. 'Thinking again?' the Duchess was VERY ugly; and secondly, because they're making such VERY.",
			"address": {
				"street": "Helmelkuja 212",
				"streetName": "Janettepolku",
				"buildingNumber": "1906",
				"city": "It\u00e4-Matti",
				"zipcode": "04662",
				"country": "Libanon",
				"county_code": "PY",
				"latitude": -6.180884,
				"longitude": -89.943589
			},
			"website": "http:\/\/jauho.net",
			"pictures": ["http:\/\/placeimg.com\/640\/480\/people", "http:\/\/placeimg.com\/640\/480\/people", "http:\/\/placeimg.com\/640\/480\/people"]
			
		},
		{
			"firstname": "Riina",
			"lastname": "Saarnivaara",
			"email": "justus.kaillomaki@jippii.fi",
			"phone": "+3645463784776",
			"birthday": "1956-07-27",
			"sexualPreference":"Hetero",
			"gender": "female",
			"biography": "Queen to play croquet.' Then they both sat silent for a few minutes, and she jumped up on to the confused clamour of the lefthand bit. * * * * * * * * * 'What a curious feeling!' said Alice; 'you.",
			"address": {
				"street": "Eemelisilta 0447",
				"streetName": "Ottokatu",
				"buildingNumber": "916",
				"city": "Pohjois-Iita",
				"zipcode": "18297",
				"country": "P\u00e4iv\u00e4ntasaajan Guinea",
				"county_code": "IN",
				"latitude": 51.943119,
				"longitude": 101.944423
			},
			"website": "http:\/\/saarenheimo.biz",
			"pictures": ["http:\/\/placeimg.com\/640\/480\/people", "http:\/\/placeimg.com\/640\/480\/people", "http:\/\/placeimg.com\/640\/480\/people"]
			
		},
		{
			"firstname": "Oona",
			"lastname": "Merel\u00e4",
			"email": "wsantanen@oikonen.com",
			"phone": "+7606415427227",
			"birthday": "1940-06-30",
			"sexualPreference":"Hetero",
			"gender": "female",
			"biography": "Mouse gave a look askance-- Said he thanked the whiting kindly, but he now hastily began again, using the ink, that was said, and went stamping about, and crept a little way out of this remark, and.",
			"address": {
				"street": "Markukselakaari 43 709",
				"streetName": "Puolakkakaarto",
				"buildingNumber": "3",
				"city": "It\u00e4-Tuomassaari",
				"zipcode": "12421",
				"country": "Kap Verde",
				"county_code": "NE",
				"latitude": 48.53076,
				"longitude": -97.4219
			},
			"website": "http:\/\/hoikkanen.biz",
			"pictures": ["http:\/\/placeimg.com\/640\/480\/people", "http:\/\/placeimg.com\/640\/480\/people", "http:\/\/placeimg.com\/640\/480\/people"]
			
		},
		{
			"firstname": "Briitta",
			"lastname": "Isotalo",
			"email": "asta94@kanala.org",
			"phone": "+5995174909486",
			"birthday": "1990-05-21",
			"sexualPreference":"Hetero",
			"gender": "male",
			"biography": "Duchess: you'd better finish the story for yourself.' 'No, please go on!' Alice said to the other, looking uneasily at the end of his tail. 'As if it began ordering people about like mad things all.",
			"address": {
				"street": "Inkerisilta 619",
				"streetName": "Neeat\u00f6yry",
				"buildingNumber": "2",
				"city": "Janipudas",
				"zipcode": "24410",
				"country": "Suriname",
				"county_code": "SO",
				"latitude": 79.649887,
				"longitude": 92.461732
			},
			"website": "http:\/\/haapala.com",
			"pictures": ["http:\/\/placeimg.com\/640\/480\/people", "http:\/\/placeimg.com\/640\/480\/people", "http:\/\/placeimg.com\/640\/480\/people"]
			
		},
		{
			"firstname": "Pirkko",
			"lastname": "Saarikivi",
			"email": "eva.jaaskelainen@luukku.com",
			"phone": "+5578759564030",
			"birthday": "2015-08-22",
			"sexualPreference":"Asexual",
			"gender": "female",
			"biography": "I--' 'Oh, don't talk about cats or dogs either, if you drink much from a bottle marked 'poison,' it is all the jurymen on to the jury, who instantly made a rush at Alice the moment she quite forgot.",
			"address": {
				"street": "Rahkakuja 1150 583",
				"streetName": "Jenikakierros",
				"buildingNumber": "43",
				"city": "Uus-Jermia",
				"zipcode": "10619",
				"country": "Malta",
				"county_code": "ZW",
				"latitude": 38.48994,
				"longitude": 100.894927
			},
			"website": "http:\/\/jaaskelainen.info",
			"pictures": ["http:\/\/placeimg.com\/640\/480\/people", "http:\/\/placeimg.com\/640\/480\/people", "http:\/\/placeimg.com\/640\/480\/people"]
			
		},
		{
			"firstname": "Mikael",
			"lastname": "Urpalainen",
			"email": "jinkeri@saksala.com",
			"phone": "+5146665816092",
			"birthday": "2000-01-25",
			"sexualPreference":"Hetero",
			"gender": "male",
			"biography": "The Queen had only one who had been anything near the house till she shook the house, quite forgetting her promise. 'Treacle,' said a whiting to a snail. \"There's a porpoise close behind us, and.",
			"address": {
				"street": "Karpelarinne 730 172",
				"streetName": "Hein\u00e4l\u00e4rinne",
				"buildingNumber": "2182",
				"city": "Fionajoki",
				"zipcode": "19887",
				"country": "Etel\u00e4-Korea",
				"county_code": "CV",
				"latitude": 63.53055,
				"longitude": -115.245845
			},
			"website": "http:\/\/kolehmainen.info",
			"pictures": ["http:\/\/placeimg.com\/640\/480\/people", "http:\/\/placeimg.com\/640\/480\/people", "http:\/\/placeimg.com\/640\/480\/people"]
			
		},
		{
			"firstname": "Antero",
			"lastname": "Saarenheimo",
			"email": "niskala.janni@jippii.fi",
			"phone": "+4085018038171",
			"birthday": "1932-09-29",
			"sexualPreference":"Hetero",
			"gender": "male",
			"biography": "Alice. 'I've so often read in the air. She did not like to have the experiment tried. 'Very true,' said the Queen, the royal children; there were TWO little shrieks, and more faintly came, carried.",
			"address": {
				"street": "Haverinenhaka 8",
				"streetName": "Juppikierros",
				"buildingNumber": "08",
				"city": "Mattijoki",
				"zipcode": "04425",
				"country": "Kypros",
				"county_code": "MA",
				"latitude": -35.120519,
				"longitude": -157.807511
			},
			"website": "http:\/\/laine.biz",
			"pictures": ["http:\/\/placeimg.com\/640\/480\/people", "http:\/\/placeimg.com\/640\/480\/people", "http:\/\/placeimg.com\/640\/480\/people"]
			
		},
		{
			"firstname": "Kirsi",
			"lastname": "Nuutti",
			"email": "matleena77@tiilikainen.org",
			"phone": "+6883642169959",
			"birthday": "1962-12-05",
			"sexualPreference":"Hetero",
			"gender": "female",
			"biography": "Rabbit noticed Alice, as she could. 'No,' said the Cat; and this was the cat.) 'I hope they'll remember her saucer of milk at tea-time. Dinah my dear! I wish I could shut up like a Jack-in-the-box.",
			"address": {
				"street": "Ahomaasilta 3",
				"streetName": "Taikakaari",
				"buildingNumber": "31",
				"city": "Uus-Eeviharju",
				"zipcode": "68276",
				"country": "Malawi",
				"county_code": "MV",
				"latitude": -79.273429,
				"longitude": 58.489344
			},
			"website": "http:\/\/braysy.com",
			"pictures": ["http:\/\/placeimg.com\/640\/480\/people", "http:\/\/placeimg.com\/640\/480\/people", "http:\/\/placeimg.com\/640\/480\/people"]
			
		},
		{
			"firstname": "Kimi",
			"lastname": "Lyly",
			"email": "uvaatanen@kouvonen.com",
			"phone": "+8207234368004",
			"birthday": "1946-01-16",
			"sexualPreference":"Hetero",
			"gender": "female",
			"biography": "And then, turning to the other guinea-pig cheered, and was looking for eggs, I know I have none, Why, I do wonder what they'll do next! If they had any sense, they'd take the place of the song.",
			"address": {
				"street": "Madet\u00f6yry 0",
				"streetName": "Juliuskulma",
				"buildingNumber": "2",
				"city": "Uus-Veikko",
				"zipcode": "21475",
				"country": "Kiina",
				"county_code": "FO",
				"latitude": -83.255541,
				"longitude": 43.911507
			},
			"website": "http:\/\/aijala.com",
			"pictures": ["http:\/\/placeimg.com\/640\/480\/people", "http:\/\/placeimg.com\/640\/480\/people", "http:\/\/placeimg.com\/640\/480\/people"]
			
		},
		{
			"firstname": "Siru",
			"lastname": "Karppinen",
			"email": "berkko@kalvo.biz",
			"phone": "+7355421359262",
			"birthday": "2001-04-10",
			"sexualPreference":"Hetero",
			"gender": "female",
			"biography": "I can do without lobsters, you know. Come on!' So they had a wink of sleep these three little sisters,' the Dormouse crossed the court, without even looking round. 'I'll fetch the executioner went.",
			"address": {
				"street": "Pauliinakulma 5 991",
				"streetName": "Rinnekaarto",
				"buildingNumber": "6",
				"city": "Unholaj\u00e4rvi",
				"zipcode": "01123",
				"country": "Kosovo",
				"county_code": "AG",
				"latitude": 7.598387,
				"longitude": -30.984744
			},
			"website": "http:\/\/syrjala.biz",
			"pictures": ["http:\/\/placeimg.com\/640\/480\/people", "http:\/\/placeimg.com\/640\/480\/people", "http:\/\/placeimg.com\/640\/480\/people"]
			
		},
		{
			"firstname": "Jirko",
			"lastname": "Luoma",
			"email": "ari.heintikainen@junkkari.info",
			"phone": "+5481893285841",
			"birthday": "1940-11-09",
			"sexualPreference":"Hetero",
			"gender": "male",
			"biography": "I was, I shouldn't like THAT!' 'Oh, you foolish Alice!' she answered herself. 'How can you learn lessons in the pictures of him), while the Mouse in the schoolroom, and though this was of very.",
			"address": {
				"street": "Taavettilapolku 5 359",
				"streetName": "Ylpp\u00f6kaari",
				"buildingNumber": "270",
				"city": "Lylyniemi",
				"zipcode": "52554",
				"country": "Etiopia",
				"county_code": "YT",
				"latitude": 13.545388,
				"longitude": 36.86411
			},
			"website": "http:\/\/ojaniemi.net",
			"pictures": ["http:\/\/placeimg.com\/640\/480\/people", "http:\/\/placeimg.com\/640\/480\/people", "http:\/\/placeimg.com\/640\/480\/people"]
			
		},
		{
			"firstname": "Eva",
			"lastname": "Nousiainen",
			"email": "aovaska@hotmail.com",
			"phone": "+1256178036065",
			"birthday": "1980-11-21",
			"sexualPreference":"Hetero",
			"gender": "female",
			"biography": "Duchess replied, in a melancholy tone. 'Nobody seems to suit them!' 'I haven't opened it yet,' said the Pigeon; 'but if you've seen them at dinn--' she checked herself hastily, and said nothing.",
			"address": {
				"street": "Aurakaarto 4 917",
				"streetName": "Arhosuokaarre",
				"buildingNumber": "2229",
				"city": "Tuppurainenharju",
				"zipcode": "62180",
				"country": "Bahrain",
				"county_code": "CC",
				"latitude": 7.128015,
				"longitude": 18.90224
			},
			"website": "http:\/\/jalonen.com",
			"pictures": ["http:\/\/placeimg.com\/640\/480\/people", "http:\/\/placeimg.com\/640\/480\/people", "http:\/\/placeimg.com\/640\/480\/people"]
			
		},
		{
			"firstname": "Jari",
			"lastname": "Nukka",
			"email": "henna91@konttinen.com",
			"phone": "+8799406785552",
			"birthday": "1992-08-12",
			"sexualPreference":"Hetero",
			"gender": "male",
			"biography": "Alice to herself, (not in a low, hurried tone. He looked anxiously at the cook, to see you any more!' And here poor Alice began in a VERY turn-up nose, much more like a steam-engine when she next.",
			"address": {
				"street": "Kultalasilta 26 409",
				"streetName": "Helin\u00e4t\u00f6yry",
				"buildingNumber": "28",
				"city": "Eerik\u00e4inenniemi",
				"zipcode": "54267",
				"country": "Valko-Ven\u00e4j\u00e4",
				"county_code": "SI",
				"latitude": -16.761159,
				"longitude": 53.572004
			},
			"website": "http:\/\/nurmi.info",
			"pictures": ["http:\/\/placeimg.com\/640\/480\/people", "http:\/\/placeimg.com\/640\/480\/people", "http:\/\/placeimg.com\/640\/480\/people"]
			
		},
		{
			"firstname": "Meeri",
			"lastname": "Raappana",
			"email": "hampus.vuorinen@jalonen.com",
			"phone": "+7856355339186",
			"birthday": "2010-02-27",
			"sexualPreference":"Hetero",
			"gender": "female",
			"biography": "The Queen turned angrily away from her as she went back to the puppy; whereupon the puppy jumped into the earth. Let me see: that would happen: '\"Miss Alice! Come here directly, and get in at once.'.",
			"address": {
				"street": "Ennikakuja 428",
				"streetName": "Corneliarinne",
				"buildingNumber": "6",
				"city": "Uusi-Santeri",
				"zipcode": "47841",
				"country": "Vatikaanivaltio",
				"county_code": "PN",
				"latitude": 79.268665,
				"longitude": 105.684522
			},
			"website": "http:\/\/suvela.com",
			"pictures": ["http:\/\/placeimg.com\/640\/480\/people", "http:\/\/placeimg.com\/640\/480\/people", "http:\/\/placeimg.com\/640\/480\/people"]
			
		},
		{
			"firstname": "Tinja",
			"lastname": "Myll\u00e4ri",
			"email": "kaisla81@hotmail.com",
			"phone": "+5984637756211",
			"birthday": "1987-06-06",
			"sexualPreference":"Hetero",
			"gender": "female",
			"biography": "Lobster Quadrille?' the Gryphon as if it please your Majesty!' the Duchess sneezed occasionally; and as the Rabbit, and had no reason to be true): If she should chance to be no doubt that it was out.",
			"address": {
				"street": "V\u00e4is\u00e4nenrinne 562",
				"streetName": "Jesperkuja",
				"buildingNumber": "3609",
				"city": "Vaaralahti",
				"zipcode": "50078",
				"country": "Trinidad ja Tobago",
				"county_code": "SC",
				"latitude": -37.862433,
				"longitude": 106.429474
			},
			"website": "http:\/\/maijala.org",
			"pictures": ["http:\/\/placeimg.com\/640\/480\/people", "http:\/\/placeimg.com\/640\/480\/people", "http:\/\/placeimg.com\/640\/480\/people"]
			
		},
		{
			"firstname": "Leo",
			"lastname": "Wirtanen",
			"email": "takkala.kimi@pirttijarvi.com",
			"phone": "+9017179672930",
			"birthday": "1973-01-31",
			"sexualPreference":"Hetero",
			"gender": "male",
			"biography": "I!' said the Queen. 'Their heads are gone, if it likes.' 'I'd rather not,' the Cat said, waving its tail when I'm angry. Therefore I'm mad.' 'I call it purring, not growling,' said Alice. 'And be.",
			"address": {
				"street": "Maijutie 5 624",
				"streetName": "Oonakaarre",
				"buildingNumber": "2",
				"city": "Paakkanenvesi",
				"zipcode": "75575",
				"country": "Peru",
				"county_code": "SH",
				"latitude": 80.122006,
				"longitude": 118.72784
			},
			"website": "http:\/\/toivanen.org",
			"pictures": ["http:\/\/placeimg.com\/640\/480\/people", "http:\/\/placeimg.com\/640\/480\/people", "http:\/\/placeimg.com\/640\/480\/people"]
			
		},
		{
			"firstname": "Aamu",
			"lastname": "Liukkonen",
			"email": "eeli14@hotmail.com",
			"phone": "+5947008654698",
			"birthday": "2002-01-11",
			"sexualPreference":"Hetero",
			"gender": "female",
			"biography": "I can't tell you just now what the next thing is, to get very tired of being upset, and their slates and pencils had been would have appeared to them she heard a little three-legged table, all made.",
			"address": {
				"street": "Hein\u00e4l\u00e4kaari 409",
				"streetName": "Jonikaarre",
				"buildingNumber": "2",
				"city": "It\u00e4-Eevi",
				"zipcode": "15925",
				"country": "Kongon demokraattinen tasavalta",
				"county_code": "SD",
				"latitude": -41.447989,
				"longitude": 84.711987
			},
			"website": "http:\/\/aitio.com",
			"pictures": ["http:\/\/placeimg.com\/640\/480\/people", "http:\/\/placeimg.com\/640\/480\/people", "http:\/\/placeimg.com\/640\/480\/people"]
			
		},
		{
			"firstname": "Juuso",
			"lastname": "Kortesj\u00e4rvi",
			"email": "atte24@aarnio.com",
			"phone": "+9949214081163",
			"birthday": "1952-04-21",
			"sexualPreference":"Hetero",
			"gender": "male",
			"biography": "Caterpillar. Alice folded her hands, wondering if anything would EVER happen in a shrill, passionate voice. 'Would YOU like cats if you hold it too long; and that he had to leave off being arches to.",
			"address": {
				"street": "Pinjakierros 7861",
				"streetName": "Samut\u00f6yry",
				"buildingNumber": "2",
				"city": "Mallalahti",
				"zipcode": "33275",
				"country": "Georgia",
				"county_code": "KM",
				"latitude": -12.089639,
				"longitude": 117.881881
			},
			"website": "http:\/\/hallila.com",
			"pictures": ["http:\/\/placeimg.com\/640\/480\/people", "http:\/\/placeimg.com\/640\/480\/people", "http:\/\/placeimg.com\/640\/480\/people"]
			
		},
		{
			"firstname": "Minea",
			"lastname": "Pirttij\u00e4rvi",
			"email": "anssi42@leppala.biz",
			"phone": "+2969754435332",
			"birthday": "1967-02-11",
			"sexualPreference":"Hetero",
			"gender": "female",
			"biography": "I should think!' (Dinah was the same thing,' said the Mouse. 'Of course,' the Dodo had paused as if she meant to take out of that is, but I THINK I can say.' This was quite surprised to find that.",
			"address": {
				"street": "Salmelat\u00f6yry 9",
				"streetName": "J\u00e4ppinent\u00f6yry",
				"buildingNumber": "805",
				"city": "Etel\u00e4-Tero",
				"zipcode": "05887",
				"country": "Argentiina",
				"county_code": "OM",
				"latitude": -34.197328,
				"longitude": -173.919525
			},
			"website": "http:\/\/kivi.com",
			"pictures": ["http:\/\/placeimg.com\/640\/480\/people", "http:\/\/placeimg.com\/640\/480\/people", "http:\/\/placeimg.com\/640\/480\/people"]
			
		},
		{
			"firstname": "Lumina",
			"lastname": "Marttinen",
			"email": "khakula@kivisto.com",
			"phone": "+8035566713441",
			"birthday": "2002-04-15",
			"sexualPreference":"Hetero",
			"gender": "female",
			"biography": "Alice! when she found herself safe in a thick wood. 'The first thing I've got to grow up again! Let me see: that would happen: '\"Miss Alice! Come here directly, and get in at the Hatter, and, just.",
			"address": {
				"street": "Oikonenrinne 887",
				"streetName": "Hildakaarre",
				"buildingNumber": "018",
				"city": "It\u00e4-Isto",
				"zipcode": "56932",
				"country": "Georgia",
				"county_code": "GG",
				"latitude": 38.426061,
				"longitude": 68.678531
			},
			"website": "http:\/\/lepomaki.com",
			"pictures": ["http:\/\/placeimg.com\/640\/480\/people", "http:\/\/placeimg.com\/640\/480\/people", "http:\/\/placeimg.com\/640\/480\/people"]
			
		},
		{
			"firstname": "Riku",
			"lastname": "Salonen",
			"email": "kauto.komulainen@jippii.fi",
			"phone": "+8400961612169",
			"birthday": "1958-12-13",
			"sexualPreference":"Hetero",
			"gender": "male",
			"biography": "Beautiful, beautiful Soup! Beau--ootiful Soo--oop! Soo--oop of the thing yourself, some winter day, I will prosecute YOU.--Come, I'll take no denial; We must have a trial: For really this morning.",
			"address": {
				"street": "Jannapolku 00",
				"streetName": "Kautokaarto",
				"buildingNumber": "1",
				"city": "Uus-Christaniemi",
				"zipcode": "82936",
				"country": "Yhdistynyt kuningaskunta",
				"county_code": "MW",
				"latitude": -1.86223,
				"longitude": 52.456069
			},
			"website": "http:\/\/einel.org",
			"pictures": ["http:\/\/placeimg.com\/640\/480\/people", "http:\/\/placeimg.com\/640\/480\/people", "http:\/\/placeimg.com\/640\/480\/people"]
			
		},
		{
			"firstname": "Briitta",
			"lastname": "Haataja",
			"email": "yvuokko@hotmail.com",
			"phone": "+5456178841772",
			"birthday": "1947-07-04",
			"sexualPreference":"Hetero",
			"gender": "male",
			"biography": "Alice. 'What IS a Caucus-race?' said Alice; not that she might as well as the doubled-up soldiers were always getting up and said, 'That's right, Five! Always lay the blame on others!' 'YOU'D better.",
			"address": {
				"street": "Anttonenhaka 9",
				"streetName": "Annekatu",
				"buildingNumber": "6700",
				"city": "Jadesaari",
				"zipcode": "27642",
				"country": "Ukraina",
				"county_code": "GG",
				"latitude": -82.209934,
				"longitude": 34.547082
			},
			"website": "http:\/\/heponen.com",
			"pictures": ["http:\/\/placeimg.com\/640\/480\/people", "http:\/\/placeimg.com\/640\/480\/people", "http:\/\/placeimg.com\/640\/480\/people"]
			
		},
		{
			"firstname": "Julius",
			"lastname": "Huurinainen",
			"email": "immonen.teijo@hotmail.com",
			"phone": "+5245142627127",
			"birthday": "1932-05-31",
			"sexualPreference":"Hetero",
			"gender": "male",
			"biography": "ME' were beautifully marked in currants. 'Well, I'll eat it,' said Alice, 'and why it is all the arches are gone from this morning,' said Alice more boldly: 'you know you're growing too.' 'Yes, but.",
			"address": {
				"street": "Beedakaari 3",
				"streetName": "Uronenhaka",
				"buildingNumber": "71",
				"city": "L\u00e4nsi-Kati",
				"zipcode": "76245",
				"country": "Dominikaaninen tasavalta",
				"county_code": "NF",
				"latitude": 12.587776,
				"longitude": 127.366569
			},
			"website": "http:\/\/hannunen.com",
			"pictures": ["http:\/\/placeimg.com\/640\/480\/people", "http:\/\/placeimg.com\/640\/480\/people", "http:\/\/placeimg.com\/640\/480\/people"]
			
		},
		{
			"firstname": "Leevi",
			"lastname": "Pakola",
			"email": "aaronen.kauto@viinanen.net",
			"phone": "+4714666023466",
			"birthday": "2004-07-23",
			"sexualPreference":"Hetero",
			"gender": "male",
			"biography": "Alice did not see anything that looked like the right size, that it made no mark; but he could go. Alice took up the other, trying every door, she ran off at once, in a natural way. 'I thought it.",
			"address": {
				"street": "Hoikkalakaarto 5 507",
				"streetName": "Akkalat\u00f6yry",
				"buildingNumber": "9",
				"city": "Repolakyl\u00e4",
				"zipcode": "43591",
				"country": "Yhdysvallat",
				"county_code": "GW",
				"latitude": 69.914086,
				"longitude": -43.23887
			},
			"website": "http:\/\/jortikka.com",
			"pictures": ["http:\/\/placeimg.com\/640\/480\/people", "http:\/\/placeimg.com\/640\/480\/people", "http:\/\/placeimg.com\/640\/480\/people"]
			
		},
		{
			"firstname": "Aino",
			"lastname": "Konttinen",
			"email": "feskela@kimalainen.fi",
			"phone": "+2714739849766",
			"birthday": "2020-06-12",
			"sexualPreference":"Hetero",
			"gender": "female",
			"biography": "CHAPTER VI. Pig and Pepper For a minute or two she stood still where she was quite pale (with passion, Alice thought), and it put more simply--\"Never imagine yourself not to make out who was reading.",
			"address": {
				"street": "Arat\u00f6yry 6496",
				"streetName": "Ronikaarto",
				"buildingNumber": "3256",
				"city": "Uusi-Jannekyl\u00e4",
				"zipcode": "81724",
				"country": "Palau",
				"county_code": "SC",
				"latitude": 10.758685,
				"longitude": 69.770469
			},
			"website": "http:\/\/ojanen.com",
			"pictures": ["http:\/\/placeimg.com\/640\/480\/people", "http:\/\/placeimg.com\/640\/480\/people", "http:\/\/placeimg.com\/640\/480\/people"]
			
		},
		{
			"firstname": "Ilona",
			"lastname": "Kerttula",
			"email": "durpalainen@hotmail.com",
			"phone": "+5265040506410",
			"birthday": "1970-10-23",
			"sexualPreference":"Hetero",
			"gender": "female",
			"biography": "The moment Alice appeared, she was up to the jury. They were indeed a queer-looking party that assembled on the whole window!' 'Sure, it does, yer honour: but it's an arm for all that.' 'Well, it's.",
			"address": {
				"street": "Jokinenkaarre 9 323",
				"streetName": "Einonenkaarto",
				"buildingNumber": "6815",
				"city": "Uus-Teppom\u00e4ki",
				"zipcode": "98194",
				"country": "It\u00e4-Timor",
				"county_code": "MU",
				"latitude": -18.327804,
				"longitude": 57.808677
			},
			"website": "http:\/\/pirttikangas.com",
			"pictures": ["http:\/\/placeimg.com\/640\/480\/people", "http:\/\/placeimg.com\/640\/480\/people", "http:\/\/placeimg.com\/640\/480\/people"]
			
		},
		{
			"firstname": "Jarno",
			"lastname": "Lind",
			"email": "laura.muhonen@yahoo.com",
			"phone": "+1998672830058",
			"birthday": "1940-11-11",
			"sexualPreference":"Hetero",
			"gender": "male",
			"biography": "I breathe\"!' 'It IS a Caucus-race?' said Alice; not that she still held the pieces of mushroom in her head, she tried her best to climb up one of them even when they liked, so that they couldn't get.",
			"address": {
				"street": "Akukatu 20 313",
				"streetName": "Hirvikulma",
				"buildingNumber": "499",
				"city": "Uus-Jermiasaari",
				"zipcode": "17384",
				"country": "Vietnam",
				"county_code": "DJ",
				"latitude": -20.220265,
				"longitude": 113.829879
			},
			"website": "http:\/\/halonen.info",
			"pictures": ["http:\/\/placeimg.com\/640\/480\/people", "http:\/\/placeimg.com\/640\/480\/people", "http:\/\/placeimg.com\/640\/480\/people"]
			
		},
		{
			"firstname": "Lila",
			"lastname": "Jortikka",
			"email": "kynsilehto.onni@raiskio.com",
			"phone": "+1878210020661",
			"birthday": "1963-12-16",
			"sexualPreference":"Hetero",
			"gender": "female",
			"biography": "First, she dreamed of little animals and birds waiting outside. The poor little feet, I wonder what you're doing!' cried Alice, jumping up and said, without even waiting to put everything upon Bill!.",
			"address": {
				"street": "Hannunent\u00f6yry 7",
				"streetName": "Santerikaarre",
				"buildingNumber": "7",
				"city": "Uusi-Minna",
				"zipcode": "78113",
				"country": "Uusi-Seelanti",
				"county_code": "VE",
				"latitude": -81.042653,
				"longitude": -176.542826
			},
			"website": "http:\/\/hekkaharju.fi",
			"pictures": ["http:\/\/placeimg.com\/640\/480\/people", "http:\/\/placeimg.com\/640\/480\/people", "http:\/\/placeimg.com\/640\/480\/people"]
			
		},
		{
			"firstname": "Eetu",
			"lastname": "Salenius",
			"email": "milla.koukkula@pesola.com",
			"phone": "+3405825734716",
			"birthday": "1962-03-04",
			"sexualPreference":"Hetero",
			"gender": "male",
			"biography": "I wish I hadn't cried so much!' Alas! it was addressed to the game. CHAPTER IX. The Mock Turtle's Story 'You can't think how glad I am very tired of this. I vote the young man said, 'And your hair.",
			"address": {
				"street": "Koivuniemirinne 735",
				"streetName": "Hakkarainenkuja",
				"buildingNumber": "03",
				"city": "Pakkalajoki",
				"zipcode": "61184",
				"country": "Saudi-Arabia",
				"county_code": "MH",
				"latitude": -45.854372,
				"longitude": -124.879868
			},
			"website": "http:\/\/helstel.fi",
			"pictures": ["http:\/\/placeimg.com\/640\/480\/people", "http:\/\/placeimg.com\/640\/480\/people", "http:\/\/placeimg.com\/640\/480\/people"]
			
		},
		{
			"firstname": "Kaste",
			"lastname": "Huusko",
			"email": "jusu.eerikainen@lyly.com",
			"phone": "+7724447970781",
			"birthday": "1960-10-11",
			"sexualPreference":"Hetero",
			"gender": "male",
			"biography": "Alice called out 'The Queen! The Queen!' and the fall was over. Alice was only sobbing,' she thought, 'it's sure to make it stop. 'Well, I'd hardly finished the goose, with the tarts, you know--'.",
			"address": {
				"street": "Maijatie 679",
				"streetName": "Hoikkanenkulma",
				"buildingNumber": "4",
				"city": "Oliviajoki",
				"zipcode": "58361",
				"country": "Mongolia",
				"county_code": "GM",
				"latitude": 79.589787,
				"longitude": -97.376452
			},
			"website": "http:\/\/kynsilehto.info",
			"pictures": ["http:\/\/placeimg.com\/640\/480\/people", "http:\/\/placeimg.com\/640\/480\/people", "http:\/\/placeimg.com\/640\/480\/people"]
			
		},
		{
			"firstname": "Markus",
			"lastname": "Herranen",
			"email": "niko79@yahoo.com",
			"phone": "+3078924839564",
			"birthday": "1996-07-20",
			"sexualPreference":"Hetero",
			"gender": "male",
			"biography": "For this must ever be A secret, kept from all the while, till at last turned sulky, and would only say, 'I am older than I am very tired of being such a hurry to change the subject of conversation.",
			"address": {
				"street": "Halkonenkaarto 4 551",
				"streetName": "Rasmusrinne",
				"buildingNumber": "13",
				"city": "Matiassaari",
				"zipcode": "67683",
				"country": "Bhutan",
				"county_code": "CL",
				"latitude": -51.323716,
				"longitude": -137.972736
			},
			"website": "http:\/\/nurmi.com",
			"pictures": ["http:\/\/placeimg.com\/640\/480\/people", "http:\/\/placeimg.com\/640\/480\/people", "http:\/\/placeimg.com\/640\/480\/people"]
			
		},
		{
			"firstname": "Jore",
			"lastname": "N\u00e4\u00e4t\u00e4nen",
			"email": "kiskonen.martta@yahoo.com",
			"phone": "+3473635565626",
			"birthday": "1954-04-27",
			"sexualPreference":"Hetero",
			"gender": "male",
			"biography": "Hatter. 'You might just as the jury asked. 'That I can't get out at the top of its mouth and began singing in its sleep 'Twinkle, twinkle, twinkle, twinkle--' and went on in a very decided tone.",
			"address": {
				"street": "Keravakaarre 4 854",
				"streetName": "Paananenrinne",
				"buildingNumber": "717",
				"city": "Eliasniemi",
				"zipcode": "52384",
				"country": "Irak",
				"county_code": "NC",
				"latitude": -63.864006,
				"longitude": 141.25471
			},
			"website": "http:\/\/jortikka.com",
			"pictures": ["http:\/\/placeimg.com\/640\/480\/people", "http:\/\/placeimg.com\/640\/480\/people", "http:\/\/placeimg.com\/640\/480\/people"]
			
		},
		{
			"firstname": "Meeri",
			"lastname": "Parkkonen",
			"email": "thelenius@hotmail.com",
			"phone": "+9038047912543",
			"birthday": "1939-05-20",
			"sexualPreference":"Hetero",
			"gender": "female",
			"biography": "Alice, 'how am I to get in?' 'There might be some sense in your knocking,' the Footman went on all the right size again; and the cool fountains. CHAPTER VIII. The Queen's Croquet-Ground A large.",
			"address": {
				"street": "Puhakkakaari 486",
				"streetName": "Petripolku",
				"buildingNumber": "4434",
				"city": "Pohjois-Nico",
				"zipcode": "12517",
				"country": "Andorra",
				"county_code": "UZ",
				"latitude": -7.516658,
				"longitude": 163.133868
			},
			"website": "http:\/\/ilmarinen.com",
			"pictures": ["http:\/\/placeimg.com\/640\/480\/people", "http:\/\/placeimg.com\/640\/480\/people", "http:\/\/placeimg.com\/640\/480\/people"]
			
		},
		{
			"firstname": "Niklas",
			"lastname": "Uosukainen",
			"email": "anita72@jippii.fi",
			"phone": "+7676476400233",
			"birthday": "1997-09-17",
			"sexualPreference":"Hetero",
			"gender": "male",
			"biography": "That's all.' 'Thank you,' said the King, and the little door into that beautiful garden--how IS that to be rude, so she bore it as a partner!' cried the Gryphon. 'I've forgotten the little glass box.",
			"address": {
				"street": "Anterot\u00f6yry 27 129",
				"streetName": "Harritie",
				"buildingNumber": "6",
				"city": "Pennanenj\u00e4rvi",
				"zipcode": "71725",
				"country": "Irak",
				"county_code": "CC",
				"latitude": -77.653613,
				"longitude": 84.705772
			},
			"website": "http:\/\/juntti.com",
			"pictures": ["http:\/\/placeimg.com\/640\/480\/people", "http:\/\/placeimg.com\/640\/480\/people", "http:\/\/placeimg.com\/640\/480\/people"]
			
		},
		{
			"firstname": "Atte",
			"lastname": "Kynsij\u00e4rvi",
			"email": "amelia25@repola.fi",
			"phone": "+5030085425318",
			"birthday": "1992-06-28",
			"sexualPreference":"Hetero",
			"gender": "female",
			"biography": "VERY unpleasant state of mind, she turned to the cur, \"Such a trial, dear Sir, With no jury or judge, would be wasting our breath.\" \"I'll be judge, I'll be jury,\" Said cunning old Fury: \"I'll try.",
			"address": {
				"street": "Tarvainenkulma 7 760",
				"streetName": "Pinjakaari",
				"buildingNumber": "6",
				"city": "Pohjois-Magnusj\u00e4rvi",
				"zipcode": "13246",
				"country": "Etiopia",
				"county_code": "LB",
				"latitude": -44.479359,
				"longitude": -110.525651
			},
			"website": "http:\/\/jaatinen.com",
			"pictures": ["http:\/\/placeimg.com\/640\/480\/people", "http:\/\/placeimg.com\/640\/480\/people", "http:\/\/placeimg.com\/640\/480\/people"]
			
		},
		{
			"firstname": "Annu",
			"lastname": "It\u00e4vaara",
			"email": "ihalainen.vilja@yahoo.com",
			"phone": "+4217977989622",
			"birthday": "2005-05-26",
			"sexualPreference":"Hetero",
			"gender": "female",
			"biography": "WOULD go with Edgar Atheling to meet William and offer him the crown. William's conduct at first was moderate. But the insolence of his shrill little voice, the name of nearly everything there.",
			"address": {
				"street": "Luminahaka 424 403",
				"streetName": "Nikulainenkuja",
				"buildingNumber": "360",
				"city": "Haapojavesi",
				"zipcode": "94775",
				"country": "Liberai",
				"county_code": "NC",
				"latitude": -41.968727,
				"longitude": 139.917316
			},
			"website": "http:\/\/typpo.com",
			"pictures": ["http:\/\/placeimg.com\/640\/480\/people", "http:\/\/placeimg.com\/640\/480\/people", "http:\/\/placeimg.com\/640\/480\/people"]
			
		},
		{
			"firstname": "Pauliina",
			"lastname": "Mannila",
			"email": "fsaarnio@oksanen.com",
			"phone": "+8454924785027",
			"birthday": "2009-01-10",
			"sexualPreference":"Hetero",
			"gender": "female",
			"biography": "Bill! catch hold of anything, but she felt a little way off, panting, with its head, it WOULD twist itself round and get ready to talk nonsense. The Queen's argument was, that anything that had.",
			"address": {
				"street": "Halkonenrinne 812 554",
				"streetName": "Janinakaari",
				"buildingNumber": "8",
				"city": "Pakarinenjoki",
				"zipcode": "60548",
				"country": "Tansania",
				"county_code": "MU",
				"latitude": 18.52104,
				"longitude": -131.109008
			},
			"website": "http:\/\/mattila.info",
			"pictures": ["http:\/\/placeimg.com\/640\/480\/people", "http:\/\/placeimg.com\/640\/480\/people", "http:\/\/placeimg.com\/640\/480\/people"]
			
		},
		{
			"firstname": "Teijo",
			"lastname": "Kontunen",
			"email": "samuli.kaurismaki@tiainen.com",
			"phone": "+3801929676008",
			"birthday": "1993-08-23",
			"sexualPreference":"Hetero",
			"gender": "male",
			"biography": "Queen say only yesterday you deserved to be ashamed of yourself,' said Alice, whose thoughts were still running on the top of her skirt, upsetting all the party went back to yesterday, because I was.",
			"address": {
				"street": "Ekkut\u00f6yry 3760 455",
				"streetName": "Mattikulma",
				"buildingNumber": "4586",
				"city": "Ojam\u00e4kiniemi",
				"zipcode": "84110",
				"country": "Kiribati",
				"county_code": "GR",
				"latitude": -80.214251,
				"longitude": -82.405474
			},
			"website": "http:\/\/ankkala.com",
			"pictures": ["http:\/\/placeimg.com\/640\/480\/people", "http:\/\/placeimg.com\/640\/480\/people", "http:\/\/placeimg.com\/640\/480\/people"]
			
		},
		{
			"firstname": "Aleksi",
			"lastname": "Vuorikoski",
			"email": "paavo.urpalainen@lepomaki.com",
			"phone": "+7676192859525",
			"birthday": "1988-04-07",
			"sexualPreference":"Hetero",
			"gender": "male",
			"biography": "The Dormouse shook its head down, and nobody spoke for some way of settling all difficulties, great or small. 'Off with her head!' Those whom she sentenced were taken into custody by the English.",
			"address": {
				"street": "Eskel\u00e4tie 1 785",
				"streetName": "Mets\u00e4ojarinne",
				"buildingNumber": "598",
				"city": "Makkonenharju",
				"zipcode": "98198",
				"country": "San Marino",
				"county_code": "SM",
				"latitude": 88.467792,
				"longitude": 8.331623
			},
			"website": "http:\/\/rinne.org",
			"pictures": ["http:\/\/placeimg.com\/640\/480\/people", "http:\/\/placeimg.com\/640\/480\/people", "http:\/\/placeimg.com\/640\/480\/people"]
			
		},
		{
			"firstname": "Briitta",
			"lastname": "Jussila",
			"email": "tero10@luukku.com",
			"phone": "+4618508751442",
			"birthday": "1943-06-27",
			"sexualPreference":"Hetero",
			"gender": "male",
			"biography": "Dinah, tell me your history, you know,' said the Hatter. He had been wandering, when a sharp hiss made her draw back in a hurry. 'No, I'll look first,' she said, 'than waste it in the book,' said.",
			"address": {
				"street": "Tiainenrinne 0",
				"streetName": "Jussilapolku",
				"buildingNumber": "6",
				"city": "Pohjois-Ilmari",
				"zipcode": "21264",
				"country": "Kenia",
				"county_code": "SG",
				"latitude": -77.255226,
				"longitude": -152.092403
			},
			"website": "http:\/\/sirvio.net",
			"pictures": ["http:\/\/placeimg.com\/640\/480\/people", "http:\/\/placeimg.com\/640\/480\/people", "http:\/\/placeimg.com\/640\/480\/people"]
			
		},
		{
			"firstname": "Oskari",
			"lastname": "Krekel\u00e4",
			"email": "uveijonen@jippii.fi",
			"phone": "+9455526156074",
			"birthday": "1943-06-22",
			"sexualPreference":"Hetero",
			"gender": "male",
			"biography": "Pigeon went on, half to Alice. 'Only a thimble,' said Alice in a confused way, 'Prizes! Prizes!' Alice had learnt several things of this sort in her hands, wondering if anything would EVER happen in.",
			"address": {
				"street": "Lottakulma 0532 706",
				"streetName": "Tukiainent\u00f6yry",
				"buildingNumber": "7",
				"city": "Uusi-Vilikoski",
				"zipcode": "97331",
				"country": "T\u0161ekki",
				"county_code": "TO",
				"latitude": 0.492461,
				"longitude": -10.716367
			},
			"website": "http:\/\/niemi.com",
			"pictures": ["http:\/\/placeimg.com\/640\/480\/people", "http:\/\/placeimg.com\/640\/480\/people", "http:\/\/placeimg.com\/640\/480\/people"]
			
		},
		{
			"firstname": "Kristian",
			"lastname": "Pirttij\u00e4rvi",
			"email": "jesper45@yahoo.com",
			"phone": "+8856832687296",
			"birthday": "1946-06-17",
			"sexualPreference":"Hetero",
			"gender": "male",
			"biography": "Conqueror.' (For, with all speed back to the jury, and the others took the hookah into its nest. Alice crouched down among the bright eager eyes were nearly out of a large ring, with the Queen, but.",
			"address": {
				"street": "Teijorinne 366 047",
				"streetName": "Jaakonmaakierros",
				"buildingNumber": "814",
				"city": "Uus-Jakeniemi",
				"zipcode": "27182",
				"country": "Kap Verde",
				"county_code": "SR",
				"latitude": -54.216323,
				"longitude": -115.770183
			},
			"website": "http:\/\/eskelinen.info",
			"pictures": ["http:\/\/placeimg.com\/640\/480\/people", "http:\/\/placeimg.com\/640\/480\/people", "http:\/\/placeimg.com\/640\/480\/people"]
			
		},
		{
			"firstname": "Vili",
			"lastname": "Hanhinen",
			"email": "pirkko.rinne@hotmail.com",
			"phone": "+3662430806406",
			"birthday": "2011-06-25",
			"sexualPreference":"Hetero",
			"gender": "female",
			"biography": "Alice: 'besides, that's not a moment that it was only a child!' The Queen smiled and passed on. 'Who ARE you doing out here? Run home this moment, and fetch me a good deal to come yet, please your.",
			"address": {
				"street": "Alijokikaarto 6652 737",
				"streetName": "Sakutie",
				"buildingNumber": "543",
				"city": "Halmekoski",
				"zipcode": "91322",
				"country": "Belgia",
				"county_code": "TM",
				"latitude": 33.99638,
				"longitude": -48.385849
			},
			"website": "http:\/\/kaakko.com",
			"pictures": ["http:\/\/placeimg.com\/640\/480\/people", "http:\/\/placeimg.com\/640\/480\/people", "http:\/\/placeimg.com\/640\/480\/people"]
			
		},
		{
			"firstname": "Teppo",
			"lastname": "Rokko",
			"email": "lehtimaki.jussi@yahoo.com",
			"phone": "+5719548096579",
			"birthday": "1962-07-19",
			"sexualPreference":"Hetero",
			"gender": "male",
			"biography": "Our family always HATED cats: nasty, low, vulgar things! Don't let me hear the Rabbit noticed Alice, as she swam about, trying to invent something!' 'I--I'm a little bit of mushroom, and raised.",
			"address": {
				"street": "Hakkarainentie 54 293",
				"streetName": "Petrikulma",
				"buildingNumber": "4",
				"city": "Tiiuharju",
				"zipcode": "96077",
				"country": "Kongon demokraattinen tasavalta",
				"county_code": "MK",
				"latitude": 40.96294,
				"longitude": -77.966782
			},
			"website": "http:\/\/einonen.info",
			"pictures": ["http:\/\/placeimg.com\/640\/480\/people", "http:\/\/placeimg.com\/640\/480\/people", "http:\/\/placeimg.com\/640\/480\/people"]
			
		}
	]
}